Workbook

Sheet Summary
A1: FRANK GOLF (GOLF WING 2号店) 収支サマリー
A2: 選択シナリオ: | B2: =Scenarios!$B$2 -> 標準 | D2: シナリオはScenarios!B2で変更
A4: ■ 資金
A5: 総初期投資 | B5: =CAPEX!$B$21 -> 12355000
A6: 出資金 | B6: =Assumptions!$B$24 -> 15000000
A7: 自己資金・融資 | B7: =Assumptions!$B$25 -> 0
A8: 開業時運転資金(手元) | B8: =Assumptions!$B$24+Assumptions!$B$25-CAPEX!$B$21 -> 2645000
A9: 最低現金残高(0-36月) | B9: =MIN(Cash_Flow!$G$4:$G$40) -> 464355
A10: 資金ショート月数 | B10: =COUNTIF(Cash_Flow!$G$5:$G$40,"<0") -> 0
A11: 投資回収期間(月) | B11: =IF(MIN(Cash_Flow!$I$5:$I$40)=9999,"36ヶ月内未回収",MIN(Cash_Flow!$I$5:$I$40)) -> 31
A13: ■ 損益(年次)
A14: 指標 | B14: Y1 | C14: Y2 | D14: Y3 | E14: 36ヶ月累計
A15: 売上高 | B15: =SUM(Monthly_PL!$L$4:$L$15) -> 13948000 | C15: =SUM(Monthly_PL!$L$16:$L$27) -> 27706000 | D15: =SUM(Monthly_PL!$L$28:$L$39) -> 36172000 | E15: =SUM(Monthly_PL!$L$4:$L$39) -> 77826000
A16: 営業利益 | B16: =SUM(Monthly_PL!$V$4:$V$15) -> -3488592.2 | C16: =SUM(Monthly_PL!$V$16:$V$27) -> 9025732.3 | D16: =SUM(Monthly_PL!$V$28:$V$39) -> 16615750 | E16: =SUM(Monthly_PL!$V$4:$V$39) -> 22152890
A17: 税引後利益 | B17: =SUM(Monthly_PL!$Y$4:$Y$15) -> -3656549.2 | C17: =SUM(Monthly_PL!$Y$16:$Y$27) -> 6318012.6 | D17: =SUM(Monthly_PL!$Y$28:$Y$39) -> 11631025 | E17: =SUM(Monthly_PL!$Y$4:$Y$39) -> 14292489
A19: ■ 主要指標
A20: 期末会員数(36ヶ月) | B20: =Monthly_PL!$G$39 -> 175
A21: 損益分岐点会員数 | B21: =BreakEven!$B$8 -> 80
A22: 現状-BEP会員差 | B22: =Monthly_PL!$G$39-BreakEven!$B$8 -> 95
A25: 注: 数値は仮置き前提に基づく初版。実データ確定で更新。

Sheet Scenarios
A1: シナリオ設定（4パターン比較）
A2: 選択シナリオ → | B2: 標準 | D2: B2で選ぶと全シート（PL/CF/損益分岐点）が自動更新
A4: パラメータ | B4: 楽観 | C4: 標準 | D4: 悲観 | E4: 最悪 | F4: 選択中(自動) | G4: 単位/備考
A5: 平均月会費(税抜) | B5: 17000 | C5: 15000 | D5: 14000 | E5: 13000 | F5: =INDEX(B5:E5,MATCH($B$2,$B$4:$E$4,0)) -> 15000 | G5: 宝塚加重平均約18,800円を保守補正
A6: 入会率(体験→入会) | B6: 0.7 | C6: 0.6 | D6: 0.25 | E6: 0.18 | F6: =INDEX(B6:E6,MATCH($B$2,$B$4:$E$4,0)) -> 0.6 | G6: 標準=体験15×60%想定。悲観/最悪は保守
A7: 退会率(月次) | B7: 0.03 | C7: 0.04 | D7: 0.06 | E7: 0.08 | F7: =INDEX(B7:E7,MATCH($B$2,$B$4:$E$4,0)) -> 0.04 | G7: 宝塚実績3.5-3.9%。新店は保守
A8: 月間体験数 Y1 | B8: 20 | C8: 15 | D8: 8 | E8: 5 | F8: =INDEX(B8:E8,MATCH($B$2,$B$4:$E$4,0)) -> 15 | G8: 標準=15/月想定
A9: 月間体験数 Y2 | B9: 22 | C9: 15 | D9: 12 | E9: 8 | F9: =INDEX(B9:E9,MATCH($B$2,$B$4:$E$4,0)) -> 15
A10: 月間体験数 Y3 | B10: 24 | C10: 15 | D10: 16 | E10: 10 | F10: =INDEX(B10:E10,MATCH($B$2,$B$4:$E$4,0)) -> 15
A11: 広告費 開業1-3ヶ月(月) | B11: 80000 | C11: 100000 | D11: 150000 | E11: 200000 | F11: =INDEX(B11:E11,MATCH($B$2,$B$4:$E$4,0)) -> 100000 | G11: 開業直後の集客投資
A12: 広告費 4ヶ月目以降(月) | B12: 40000 | C12: 50000 | D12: 90000 | E12: 120000 | F12: =INDEX(B12:E12,MATCH($B$2,$B$4:$E$4,0)) -> 50000 | G12: 標準=5万/月
A13: 人件費(月) | B13: 500000 | C13: 580000 | D13: 650000 | E13: 750000 | F13: =INDEX(B13:E13,MATCH($B$2,$B$4:$E$4,0)) -> 580000 | G13: 無人化前提。最悪は増員
A14: 物販ARPU(会員/月) | B14: 3000 | C14: 2000 | D14: 1500 | E14: 1000 | F14: =INDEX(B14:E14,MATCH($B$2,$B$4:$E$4,0)) -> 2000 | G14: 会員1人あたり月物販
A15: 開業時先行会員数 | B15: 40 | C15: 30 | D15: 5 | E15: 3 | F15: =INDEX(B15:E15,MATCH($B$2,$B$4:$E$4,0)) -> 30 | G15: 標準=開業時30名想定
A16: 追加CAPEX(初期不良/やり直し) | B16: 0 | C16: 0 | D16: 300000 | E16: 800000 | F16: =INDEX(B16:E16,MATCH($B$2,$B$4:$E$4,0)) -> 0 | G16: 悲観/最悪で発生

Sheet Assumptions
A1: 前提条件（入力の集約）
A2: 黄=入力（変更可）／緑=他シート参照。他シートは原則ここを参照
A4: ■ 基本前提
A5: 会員上限(capacity) | B5: 200
A6: 入会金(税抜) | B6: 30000
A7: 体験単価(税抜) | B7: 2000
A8: 物販原価率 | B8: 0.65
A9: 決済手数料率 | B9: 0.03
A10: 決済適用率(カード等比率) | B10: 0.9
A11: 減価償却年数(設備) | B11: 7
A12: 実効税率 | B12: 0.3
A13: 家賃(月) | B13: 400000
A14: 光熱費(月) | B14: 80000
A15: 通信費(月) | B15: 15000
A16: 保険(月) | B16: 12000
... A25: 自己資金・融資 | B25: 0
A27: ■ 選択シナリオの反映値（自動）
A28: 平均月会費(税抜) | B28: =Scenarios!F5 -> 15000
A29: 入会率 | B29: =Scenarios!F6 -> 0.6
A30: 退会率(月) | B30: =Scenarios!F7 -> 0.04
A31: 月間体験数 Y1 | B31: =Scenarios!F8 -> 15
A32: 月間体験数 Y2 | B32: =Scenarios!F9 -> 15
A33: 月間体験数 Y3 | B33: =Scenarios!F10 -> 15
A34: 広告費 開業1-3ヶ月(月) | B34: =Scenarios!F11 -> 100000
A35: 広告費 4ヶ月目以降(月) | B35: =Scenarios!F12 -> 50000
A36: 人件費(月) | B36: =Scenarios!F13 -> 580000
A37: 物販ARPU(月) | B37: =Scenarios!F14 -> 2000
A38: 開業時先行会員数 | B38: =Scenarios!F15 -> 30
A39: 追加CAPEX | B39: =Scenarios!F16 -> 0
A41: ■ その他固定費の合計（自動）
A42: その他固定費小計(家賃/人件費/広告除く) | B42: =B14+B15+B16+B17+B18+B19+B20+B21 -> 182000
A43: 予備費 | B43: =B42*B22 -> 5460
A44: その他固定費 計 | B44: =B42+B43 -> 187460
A46: ■ 前受け（月会費先取り）
A47: 前受けON(1=有効,0=無効) | B47: 1 | C47: 3ヶ月前取り等の運転資本効果をCFに反映
A48: 前受けフロート係数(月分) | B48: 1.5 | C48: 3ヶ月前取り≒1.5。会員増加分×係数×会費が現金前倒し
A49: ■ 後日投資（防犯・セキュリティ）
A50: 防犯・セキュリティ投資額 | B50: 400000 | C50: 24時間無人化。開業後に実施しCAPEXを後ろ倒し
A51: 実施月(開業何ヶ月後) | B51: 6

Sheet CAPEX
A1: 初期投資（CAPEX）内訳
A2: ※既存楽観案(約10,340千円)は保証金・予備費・開業前費用が未計上の疑い。本表は保守計上。
A4: 項目 | B4: 金額 | C4: 備考
A5: 内装工事(居抜き) | B5: 1800000 | C5: 居抜き活用で圧縮。造作・打席ブース中心
A6: 電気工事 | B6: 800000 | C6: 分電盤・打席電源・照明
A7: 空調・換気・設備工事 | B7: 1000000 | C7: 打席発熱対応で増設
A8: 防音・安全対策 | B8: 800000 | C8: 防音・防球・防護
A9: シミュレーター・機材(2打席) | B9: 2500000 | C9: 機種で50万〜250万/席。中位想定
A10: PC・ネットワーク・AV | B10: 500000
A11: 什器・備品 | B11: 500000
A12: 看板・サイン | B12: 400000
A13: 決済・POS環境 | B13: 150000
A14: HP制作・初期ブランディング | B14: 300000 | C14: YOZAN WEB。既存テンプレ流用
A15: 開業前費用(採用・研修・内覧) | B15: 300000
A16: 設備小計 | B16: =SUM(B5:B15) -> 9050000
A17: 予備費(10%) | B17: =B16*0.1 -> 905000
A18: CAPEX計(減価償却対象) | B18: =B16+B17 -> 9955000
A19: 保証金・敷金 | B19: =Assumptions!$B$13*Assumptions!$B$23 -> 2400000
A20: 追加CAPEX(シナリオ) | B20: =Assumptions!$B$39 -> 0
A21: 総初期投資 | B21: =B18+B19+B20 -> 12355000

Sheet OPEX
A1: 月次コスト内訳（OPEX）
A3: 区分 | B3: 項目 | C3: 金額(月) | D3: 種別 | E3: 備考
A4: 固定費 | B4: 家賃 | C4: =Assumptions!$B$13 -> 400000 | D4: 固定
A5: 固定費 | B5: 人件費 | C5: =Assumptions!$B$36 -> 580000 | D5: 固定(シナリオ) | E5: 最悪は増員
A6: 固定費 | B6: 広告費(開業1-3ヶ月) | C6: =Assumptions!$B$34 -> 100000 | D6: 固定(期間変動) | E6: 開業直後
A7: 固定費 | B7: 広告費(4ヶ月〜) | C7: =Assumptions!$B$35 -> 50000 | D7: 固定(期間変動) | E7: 4ヶ月目以降
A8: 固定費 | B8: 光熱費 | C8: =Assumptions!$B$14 -> 80000 | D8: 固定
A9: 固定費 | B9: 通信費 | C9: =Assumptions!$B$15 -> 15000 | D9: 固定
A10: 固定費 | B10: 保険 | C10: =Assumptions!$B$16 -> 12000 | D10: 固定
A11: 固定費 | B11: システム費 | C11: =Assumptions!$B$17 -> 10000 | D11: 固定 | E11: 予約/会員/機材月額
A12: 固定費 | B12: 清掃費 | C12: =Assumptions!$B$18 -> 20000 | D12: 固定
A13: 固定費 | B13: 修繕・設備更新積立 | C13: =Assumptions!$B$19 -> 30000 | D13: 固定
A14: 固定費 | B14: 消耗品費 | C14: =Assumptions!$B$20 -> 15000 | D14: 固定
A15: 固定費 | B15: 税理士費用 | C15: =Assumptions!$B$21 -> 0 | D15: 固定
A16: 固定費 | B16: 予備費 | C16: =Assumptions!$B$43 -> 5460 | D16: 固定 | E16: 対その他固定費3%
A17: 変動費 | B17: 決済手数料 | C17: 売上×3%×適用率 | D17: 変動 | E17: Monthly_PLで計算
A18: 変動費 | B18: 物販原価 | C18: 物販売上×65% | D18: 変動 | E18: Monthly_PLで計算
A20: 固定費計(Y1,広告Y1) | C20: =C4+C5+C6+C8+C9+C10+C11+C12+C13+C14+C15+C16 -> 1267460
A21: 固定費計(Y2-3,広告Y2-3) | C21: =C4+C5+C7+C8+C9+C10+C11+C12+C13+C14+C15+C16 -> 1217460

Sheet Monthly_PL
A1: 月次損益計画（36ヶ月）
A2: 会員動態→売上→変動費→固定費→営業利益。選択シナリオで自動更新。
A3: 月 | B3: 年 | C3: 期首会員 | D3: 体験数 | E3: 入会数 | F3: 退会数 | G3: 期末会員 | H3: 月会費売上 | I3: 入会金売上 | J3: 体験売上 | K3: 物販売上 | L3: 売上合計 | M3: 物販原価 | N3: 決済手数料 | O3: 変動費計 | P3: 家賃 | Q3: 人件費 | R3: 広告費 | S3: その他固定費 | T3: 固定費計 | U3: 減価償却 | V3: 営業利益 | W3: 税前利益 | X3: 法人税等 | Y3: 税引後利益
A4: 1 | B4: =ROUNDUP(A4/12,0) -> 1 | C4: =Assumptions!$B$38 -> 30 | D4: =ROUND(IF(B4=1,Assumptions!$B$31,IF(B4=2,Assumptions!$B$32,Assumptions!$B$33))*MIN(1,A4/6),0) -> 3 | E4: =MAX(0,MIN(ROUND(D4*Assumptions!$B$29,0),Assumptions!$B$5-(C4-F4))) -> 2 | F4: =ROUND(C4*Assumptions!$B$30,0) -> 1 | G4: =MAX(0,MIN(Assumptions!$B$5,C4+E4-F4)) -> 31 | H4: =C4*Assumptions!$B$28 -> 450000 | I4: =E4*Assumptions!$B$6 -> 60000 | J4: =D4*Assumptions!$B$7 -> 6000 | K4: =C4*Assumptions!$B$37 -> 60000 | L4: =SUM(H4:K4) -> 576000 | M4: =K4*Assumptions!$B$8 -> 39000 | N4: =L4*Assumptions!$B$9*Assumptions!$B$10 -> 15552 | O4: =M4+N4 -> 54552 | P4: =Assumptions!$B$13 -> 400000 | Q4: =Assumptions!$B$36 -> 580000 | R4: =IF(A4<=3,Assumptions!$B$34,Assumptions!$B$35) -> 100000 | S4: =Assumptions!$B$44 -> 187460 | T4: =P4+Q4+R4+S4 -> 1267460 | U4: =(CAPEX!$B$18+CAPEX!$B$20)/(Assumptions!$B$11*12)+IF(A4>=Assumptions!$B$51,Assumptions!$B$50/(Assumptions!$B$11*12),0) -> 118511.9 | V4: =L4-O4-T4-U4 -> -864523.9 | W4: =V4 -> -864523.9 | X4: =MAX(0,W4)*Assumptions!$B$12 -> 0 | Y4: =W4-X4 -> -864523.9
A5: 2 | B5: =ROUNDUP(A5/12,0) -> 1 | C5: =G4 -> 31 | D5: =ROUND(IF(B5=1,Assumptions!$B$31,IF(B5=2,Assumptions!$B$32,Assumptions!$B$33))*MIN(1,A5/6),0) -> 5 | E5: =MAX(0,MIN(ROUND(D5*Assumptions!$B$29,0),Assumptions!$B$5-(C5-F5))) -> 3 | F5: =ROUND(C5*Assumptions!$B$30,0) -> 1 | G5: =MAX(0,MIN(Assumptions!$B$5,C5+E5-F5)) -> 33 | H5: =C5*Assumptions!$B$28 -> 465000 | I5: =E5*Assumptions!$B$6 -> 90000 | J5: =D5*Assumptions!$B$7 -> 10000 | K5: =C5*Assumptions!$B$37 -> 62000 | L5: =SUM(H5:K5) -> 627000 | M5: =K5*Assumptions!$B$8 -> 40300 | N5: =L5*Assumptions!$B$9*Assumptions!$B$10 -> 16929 | O5: =M5+N5 -> 57229 | P5: =Assumptions!$B$13 -> 400000 | Q5: =Assumptions!$B$36 -> 580000 | R5: =IF(A5<=3,Assumptions!$B$34,Assumptions!$B$35) -> 100000 | S5: =Assumptions!$B$44 -> 187460 | T5: =P5+Q5+R5+S5 -> 1267460 | U5: =(CAPEX!$B$18+CAPEX!$B$20)/(Assumptions!$B$11*12)+IF(A5>=Assumptions!$B$51,Assumptions!$B$50/(Assumptions!$B$11*12),0) -> 118511.9 | V5: =L5-O5-T5-U5 -> -816200.9 | W5: =V5 -> -816200.9 | X5: =MAX(0,W5)*Assumptions!$B$12 -> 0 | Y5: =W5-X5 -> -816200.9
A6: 3 | B6: =ROUNDUP(A6/12,0) -> 1 | C6: =G5 -> 33 | D6: =ROUND(IF(B6=1,Assumptions!$B$31,IF(B6=2,Assumptions!$B$32,Assumptions!$B$33))*MIN(1,A6/6),0) -> 8 | E6: =MAX(0,MIN(ROUND(D6*Assumptions!$B$29,0),Assumptions!$B$5-(C6-F6))) -> 5 | F6: =ROUND(C6*Assumptions!$B$30,0) -> 1 | G6: =MAX(0,MIN(Assumptions!$B$5,C6+E6-F6)) -> 37 | H6: =C6*Assumptions!$B$28 -> 495000 | I6: =E6*Assumptions!$B$6 -> 150000 | J6: =D6*Assumptions!$B$7 -> 16000 | K6: =C6*Assumptions!$B$37 -> 66000 | L6: =SUM(H6:K6) -> 727000 | M6: =K6*Assumptions!$B$8 -> 42900 | N6: =L6*Assumptions!$B$9*Assumptions!$B$10 -> 19629 | O6: =M6+N6 -> 62529 | P6: =Assumptions!$B$13 -> 400000 | Q6: =Assumptions!$B$36 -> 580000 | R6: =IF(A6<=3,Assumptions!$B$34,Assumptions!$B$35) -> 100000 | S6: =Assumptions!$B$44 -> 187460 | T6: =P6+Q6+R6+S6 -> 1267460 | U6: =(CAPEX!$B$18+CAPEX!$B$20)/(Assumptions!$B$11*12)+IF(A6>=Assumptions!$B$51,Assumptions!$B$50/(Assumptions!$B$11*12),0) -> 118511.9 | V6: =L6-O6-T6-U6 -> -721500.9 | W6: =V6 -> -721500.9 | X6: =MAX(0,W6)*Assumptions!$B$12 -> 0 | Y6: =W6-X6 -> -721500.9
A7: 4 | B7: =ROUNDUP(A7/12,0) -> 1 | C7: =G6 -> 37 | D7: =ROUND(IF(B7=1,Assumptions!$B$31,IF(B7=2,Assumptions!$B$32,Assumptions!$B$33))*MIN(1,A7/6),0) -> 10 | E7: =MAX(0,MIN(ROUND(D7*Assumptions!$B$29,0),Assumptions!$B$5-(C7-F7))) -> 6 | F7: =ROUND(C7*Assumptions!$B$30,0) -> 1 | G7: =MAX(0,MIN(Assumptions!$B$5,C7+E7-F7)) -> 42 | H7: =C7*Assumptions!$B$28 -> 555000 | I7: =E7*Assumptions!$B$6 -> 180000 | J7: =D7*Assumptions!$B$7 -> 20000 | K7: =C7*Assumptions!$B$37 -> 74000 | L7: =SUM(H7:K7) -> 829000 | M7: =K7*Assumptions!$B$8 -> 48100 | N7: =L7*Assumptions!$B$9*Assumptions!$B$10 -> 22383 | O7: =M7+N7 -> 70483 | P7: =Assumptions!$B$13 -> 400000 | Q7: =Assumptions!$B$36 -> 580000 | R7: =IF(A7<=3,Assumptions!$B$34,Assumptions!$B$35) -> 50000 | S7: =Assumptions!$B$44 -> 187460 | T7: =P7+Q7+R7+S7 -> 1217460 | U7: =(CAPEX!$B$18+CAPEX!$B$20)/(Assumptions!$B$11*12)+IF(A7>=Assumptions!$B$51,Assumptions!$B$50/(Assumptions!$B$11*12),0) -> 118511.9 | V7: =L7-O7-T7-U7 -> -577454.9 | W7: =V7 -> -577454.9 | X7: =MAX(0,W7)*Assumptions!$B$12 -> 0 | Y7: =W7-X7 -> -577454.9
A8: 5 | B8: =ROUNDUP(A8/12,0) -> 1 | C8: =G7 -> 42 | D8: =ROUND(IF(B8=1,Assumptions!$B$31,IF(B8=2,Assumptions!$B$32,Assumptions!$B$33))*MIN(1,A8/6),0) -> 13 | E8: =MAX(0,MIN(ROUND(D8*Assumptions!$B$29,0),Assumptions!$B$5-(C8-F8))) -> 8 | F8: =ROUND(C8*Assumptions!$B$30,0) -> 2 | G8: =MAX(0,MIN(Assumptions!$B$5,C8+E8-F8)) -> 48 | H8: =C8*Assumptions!$B$28 -> 630000 | I8: =E8*Assumptions!$B$6 -> 240000 | J8: =D8*Assumptions!$B$7 -> 26000 | K8: =C8*Assumptions!$B$37 -> 84000 | L8: =SUM(H8:K8) -> 980000 | M8: =K8*Assumptions!$B$8 -> 54600 | N8: =L8*Assumptions!$B$9*Assumptions!$B$10 -> 26460 | O8: =M8+N8 -> 81060 | P8: =Assumptions!$B$13 -> 400000 | Q8: =Assumptions!$B$36 -> 580000 | R8: =IF(A8<=3,Assumptions!$B$34,Assumptions!$B$35) -> 50000 | S8: =Assumptions!$B$44 -> 187460 | T8: =P8+Q8+R8+S8 -> 1217460 | U8: =(CAPEX!$B$18+CAPEX!$B$20)/(Assumptions!$B$11*12)+IF(A8>=Assumptions!$B$51,Assumptions!$B$50/(Assumptions!$B$11*12),0) -> 118511.9 | V8: =L8-O8-T8-U8 -> -437031.9 | W8: =V8 -> -437031.9 | X8: =MAX(0,W8)*Assumptions!$B$12 -> 0 | Y8: =W8-X8 -> -437031.9
A9: 6 | B9: =ROUNDUP(A9/12,0) -> 1 | C9: =G8 -> 48 | D9: =ROUND(IF(B9=1,Assumptions!$B$31,IF(B9=2,Assumptions!$B$32,Assumptions!$B$33))*MIN(1,A9/6),0) -> 15 | E9: =MAX(0,MIN(ROUND(D9*Assumptions!$B$29,0),Assumptions!$B$5-(C9-F9))) -> 9 | F9: =ROUND(C9*Assumptions!$B$30,0) -> 2 | G9: =MAX(0,MIN(Assumptions!$B$5,C9+E9-F9)) -> 55 | H9: =C9*Assumptions!$B$28 -> 720000 | I9: =E9*Assumptions!$B$6 -> 270000 | J9: =D9*Assumptions!$B$7 -> 30000 | K9: =C9*Assumptions!$B$37 -> 96000 | L9: =SUM(H9:K9) -> 1116000 | M9: =K9*Assumptions!$B$8 -> 62400 | N9: =L9*Assumptions!$B$9*Assumptions!$B$10 -> 30132 | O9: =M9+N9 -> 92532 | P9: =Assumptions!$B$13 -> 400000 | Q9: =Assumptions!$B$36 -> 580000 | R9: =IF(A9<=3,Assumptions!$B$34,Assumptions!$B$35) -> 50000 | S9: =Assumptions!$B$44 -> 187460 | T9: =P9+Q9+R9+S9 -> 1217460 | U9: =(CAPEX!$B$18+CAPEX!$B$20)/(Assumptions!$B$11*12)+IF(A9>=Assumptions!$B$51,Assumptions!$B$50/(Assumptions!$B$11*12),0) -> 123273.81 | V9: =L9-O9-T9-U9 -> -317265.81 | W9: =V9 -> -317265.81 | X9: =MAX(0,W9)*Assumptions!$B$12 -> 0 | Y9: =W9-X9 -> -317265.81
A10: 7 | B10: =ROUNDUP(A10/12,0) -> 1 | C10: =G9 -> 55 | D10: =ROUND(IF(B10=1,Assumptions!$B$31,IF(B10=2,Assumptions!$B$32,Assumptions!$B$33))*MIN(1,A10/6),0) -> 15 | E10: =MAX(0,MIN(ROUND(D10*Assumptions!$B$29,0),Assumptions!$B$5-(C10-F10))) -> 9 | F10: =ROUND(C10*Assumptions!$B$30,0) -> 2 | G10: =MAX(0,MIN(Assumptions!$B$5,C10+E10-F10)) -> 62 | H10: =C10*Assumptions!$B$28 -> 825000 | I10: =E10*Assumptions!$B$6 -> 270000 | J10: =D10*Assumptions!$B$7 -> 30000 | K10: =C10*Assumptions!$B$37 -> 110000 | L10: =SUM(H10:K10) -> 1235000 | M10: =K10*Assumptions!$B$8 -> 71500 | N10: =L10*Assumptions!$B$9*Assumptions!$B$10 -> 33345 | O10: =M10+N10 -> 104845 | P10: =Assumptions!$B$13 -> 400000 | Q10: =Assumptions!$B$36 -> 580000 | R10: =IF(A10<=3,Assumptions!$B$34,Assumptions!$B$35) -> 50000 | S10: =Assumptions!$B$44 -> 187460 | T10: =P10+Q10+R10+S10 -> 1217460 | U10: =(CAPEX!$B$18+CAPEX!$B$20)/(Assumptions!$B$11*12)+IF(A10>=Assumptions!$B$51,Assumptions!$B$50/(Assumptions!$B$11*12),0) -> 123273.81 | V10: =L10-O10-T10-U10 -> -210578.81 | W10: =V10 -> -210578.81 | X10: =MAX(0,W10)*Assumptions!$B$12 -> 0 | Y10: =W10-X10 -> -210578.81
A11: 8 | B11: =ROUNDUP(A11/12,0) -> 1 | C11: =G10 -> 62 | D11: =ROUND(IF(B11=1,Assumptions!$B$31,IF(B11=2,Assumptions!$B$32,Assumptions!$B$33))*MIN(1,A11/6),0) -> 15 | E11: =MAX(0,MIN(ROUND(D11*Assumptions!$B$29,0),Assumptions!$B$5-(C11-F11))) -> 9 | F11: =ROUND(C11*Assumptions!$B$30,0) -> 2 | G11: =MAX(0,MIN(Assumptions!$B$5,C11+E11-F11)) -> 69 | H11: =C11*Assumptions!$B$28 -> 930000 | I11: =E11*Assumptions!$B$6 -> 270000 | J11: =D11*Assumptions!$B$7 -> 30000 | K11: =C11*Assumptions!$B$37 -> 124000 | L11: =SUM(H11:K11) -> 1354000 | M11: =K11*Assumptions!$B$8 -> 80600 | N11: =L11*Assumptions!$B$9*Assumptions!$B$10 -> 36558 | O11: =M11+N11 -> 117158 | P11: =Assumptions!$B$13 -> 400000 | Q11: =Assumptions!$B$36 -> 580000 | R11: =IF(A11<=3,Assumptions!$B$34,Assumptions!$B$35) -> 50000 | S11: =Assumptions!$B$44 -> 187460 | T11: =P11+Q11+R11+S11 -> 1217460 | U11: =(CAPEX!$B$18+CAPEX!$B$20)/(Assumptions!$B$11*12)+IF(A11>=Assumptions!$B$51,Assumptions!$B$50/(Assumptions!$B$11*12),0) -> 123273.81 | V11: =L11-O11-T11-U11 -> -103891.81 | W11: =V11 -> -103891.81 | X11: =MAX(0,W11)*Assumptions!$B$12 -> 0 | Y11: =W11-X11 -> -103891.81
A12: 9 | B12: =ROUNDUP(A12/12,0) -> 1 | C12: =G11 -> 69 | D12: =ROUND(IF(B12=1,Assumptions!$B$31,IF(B12=2,Assumptions!$B$32,Assumptions!$B$33))*MIN(1,A12/6),0) -> 15 | E12: =MAX(0,MIN(ROUND(D12*Assumptions!$B$29,0),Assumptions!$B$5-(C12-F12))) -> 9 | F12: =ROUND(C12*Assumptions!$B$30,0) -> 3 | G12: =MAX(0,MIN(Assumptions!$B$5,C12+E12-F12)) -> 75 | H12: =C12*Assumptions!$B$28 -> 1035000 | I12: =E12*Assumptions!$B$6 -> 270000 | J12: =D12*Assumptions!$B$7 -> 30000 | K12: =C12*Assumptions!$B$37 -> 138000 | L12: =SUM(H12:K12) -> 1473000 | M12: =K12*Assumptions!$B$8 -> 89700 | N12: =L12*Assumptions!$B$9*Assumptions!$B$10 -> 39771 | O12: =M12+N12 -> 129471 | P12: =Assumptions!$B$13 -> 400000 | Q12: =Assumptions!$B$36 -> 580000 | R12: =IF(A12<=3,Assumptions!$B$34,Assumptions!$B$35) -> 50000 | S12: =Assumptions!$B$44 -> 187460 | T12: =P12+Q12+R12+S12 -> 1217460 | U12: =(CAPEX!$B$18+CAPEX!$B$20)/(Assumptions!$B$11*12)+IF(A12>=Assumptions!$B$51,Assumptions!$B$50/(Assumptions!$B$11*12),0) -> 123273.81 | V12: =L12-O12-T12-U12 -> 2795.1905 | W12: =V12 -> 2795.1905 | X12: =MAX(0,W12)*Assumptions!$B$12 -> 838.55714 | Y12: =W12-X12 -> 1956.6333
A13: 10 | B13: =ROUNDUP(A13/12,0) -> 1 | C13: =G12 -> 75 | D13: =ROUND(IF(B13=1,Assumptions!$B$31,IF(B13=2,Assumptions!$B$32,Assumptions!$B$33))*MIN(1,A13/6),0) -> 15 | E13: =MAX(0,MIN(ROUND(D13*Assumptions!$B$29,0),Assumptions!$B$5-(C13-F13))) -> 9 | F13: =ROUND(C13*Assumptions!$B$30,0) -> 3 | G13: =MAX(0,MIN(Assumptions!$B$5,C13+E13-F13)) -> 81 | H13: =C13*Assumptions!$B$28 -> 1125000 | I13: =E13*Assumptions!$B$6 -> 270000 | J13: =D13*Assumptions!$B$7 -> 30000 | K13: =C13*Assumptions!$B$37 -> 150000 | L13: =SUM(H13:K13) -> 1575000 | M13: =K13*Assumptions!$B$8 -> 97500 | N13: =L13*Assumptions!$B$9*Assumptions!$B$10 -> 42525 | O13: =M13+N13 -> 140025 | P13: =Assumptions!$B$13 -> 400000 | Q13: =Assumptions!$B$36 -> 580000 | R13: =IF(A13<=3,Assumptions!$B$34,Assumptions!$B$35) -> 50000 | S13: =Assumptions!$B$44 -> 187460 | T13: =P13+Q13+R13+S13 -> 1217460 | U13: =(CAPEX!$B$18+CAPEX!$B$20)/(Assumptions!$B$11*12)+IF(A13>=Assumptions!$B$51,Assumptions!$B$50/(Assumptions!$B$11*12),0) -> 123273.81 | V13: =L13-O13-T13-U13 -> 94241.19 | W13: =V13 -> 94241.19 | X13: =MAX(0,W13)*Assumptions!$B$12 -> 28272.357 | Y13: =W13-X13 -> 65968.833
A14: 11 | B14: =ROUNDUP(A14/12,0) -> 1 | C14: =G13 -> 81 | D14: =ROUND(IF(B14=1,Assumptions!$B$31,IF(B14=2,Assumptions!$B$32,Assumptions!$B$33))*MIN(1,A14/6),0) -> 15 | E14: =MAX(0,MIN(ROUND(D14*Assumptions!$B$29,0),Assumptions!$B$5-(C14-F14))) -> 9 | F14: =ROUND(C14*Assumptions!$B$30,0) -> 3 | G14: =MAX(0,MIN(Assumptions!$B$5,C14+E14-F14)) -> 87 | H14: =C14*Assumptions!$B$28 -> 1215000 | I14: =E14*Assumptions!$B$6 -> 270000 | J14: =D14*Assumptions!$B$7 -> 30000 | K14: =C14*Assumptions!$B$37 -> 162000 | L14: =SUM(H14:K14) -> 1677000 | M14: =K14*Assumptions!$B$8 -> 105300 | N14: =L14*Assumptions!$B$9*Assumptions!$B$10 -> 45279 | O14: =M14+N14 -> 150579 | P14: =Assumptions!$B$13 -> 400000 | Q14: =Assumptions!$B$36 -> 580000 | R14: =IF(A14<=3,Assumptions!$B$34,Assumptions!$B$35) -> 50000 | S14: =Assumptions!$B$44 -> 187460 | T14: =P14+Q14+R14+S14 -> 1217460 | U14: =(CAPEX!$B$18+CAPEX!$B$20)/(Assumptions!$B$11*12)+IF(A14>=Assumptions!$B$51,Assumptions!$B$50/(Assumptions!$B$11*12),0) -> 123273.81 | V14: =L14-O14-T14-U14 -> 185687.19 | W14: =V14 -> 185687.19 | X14: =MAX(0,W14)*Assumptions!$B$12 -> 55706.157 | Y14: =W14-X14 -> 129981.03
A15: 12 | B15: =ROUNDUP(A15/12,0) -> 1 | C15: =G14 -> 87 | D15: =ROUND(IF(B15=1,Assumptions!$B$31,IF(B15=2,Assumptions!$B$32,Assumptions!$B$33))*MIN(1,A15/6),0) -> 15 | E15: =MAX(0,MIN(ROUND(D15*Assumptions!$B$29,0),Assumptions!$B$5-(C15-F15))) -> 9 | F15: =ROUND(C15*Assumptions!$B$30,0) -> 3 | G15: =MAX(0,MIN(Assumptions!$B$5,C15+E15-F15)) -> 93 | H15: =C15*Assumptions!$B$28 -> 1305000 | I15: =E15*Assumptions!$B$6 -> 270000 | J15: =D15*Assumptions!$B$7 -> 30000 | K15: =C15*Assumptions!$B$37 -> 174000 | L15: =SUM(H15:K15) -> 1779000 | M15: =K15*Assumptions!$B$8 -> 113100 | N15: =L15*Assumptions!$B$9*Assumptions!$B$10 -> 48033 | O15: =M15+N15 -> 161133 | P15: =Assumptions!$B$13 -> 400000 | Q15: =Assumptions!$B$36 -> 580000 | R15: =IF(A15<=3,Assumptions!$B$34,Assumptions!$B$35) -> 50000 | S15: =Assumptions!$B$44 -> 187460 | T15: =P15+Q15+R15+S15 -> 1217460 | U15: =(CAPEX!$B$18+CAPEX!$B$20)/(Assumptions!$B$11*12)+IF(A15>=Assumptions!$B$51,Assumptions!$B$50/(Assumptions!$B$11*12),0) -> 123273.81 | V15: =L15-O15-T15-U15 -> 277133.19 | W15: =V15 -> 277133.19 | X15: =MAX(0,W15)*Assumptions!$B$12 -> 83139.957 | Y15: =W15-X15 -> 193993.23
A16: 13 | B16: =ROUNDUP(A16/12,0) -> 2 | C16: =G15 -> 93 | D16: =ROUND(IF(B16=1,Assumptions!$B$31,IF(B16=2,Assumptions!$B$32,Assumptions!$B$33))*MIN(1,A16/6),0) -> 15 | E16: =MAX(0,MIN(ROUND(D16*Assumptions!$B$29,0),Assumptions!$B$5-(C16-F16))) -> 9 | F16: =ROUND(C16*Assumptions!$B$30,0) -> 4 | G16: =MAX(0,MIN(Assumptions!$B$5,C16+E16-F16)) -> 98 | H16: =C16*Assumptions!$B$28 -> 1395000 | I16: =E16*Assumptions!$B$6 -> 270000 | J16: =D16*Assumptions!$B$7 -> 30000 | K16: =C16*Assumptions!$B$37 -> 186000 | L16: =SUM(H16:K16) -> 1881000 | M16: =K16*Assumptions!$B$8 -> 120900 | N16: =L16*Assumptions!$B$9*Assumptions!$B$10 -> 50787 | O16: =M16+N16 -> 171687 | P16: =Assumptions!$B$13 -> 400000 | Q16: =Assumptions!$B$36 -> 580000 | R16: =IF(A16<=3,Assumptions!$B$34,Assumptions!$B$35) -> 50000 | S16: =Assumptions!$B$44 -> 187460 | T16: =P16+Q16+R16+S16 -> 1217460 | U16: =(CAPEX!$B$18+CAPEX!$B$20)/(Assumptions!$B$11*12)+IF(A16>=Assumptions!$B$51,Assumptions!$B$50/(Assumptions!$B$11*12),0) -> 123273.81 | V16: =L16-O16-T16-U16 -> 368579.19 | W16: =V16 -> 368579.19 | X16: =MAX(0,W16)*Assumptions!$B$12 -> 110573.76 | Y16: =W16-X16 -> 258005.43
... A39: 36 | B39: =ROUNDUP(A39/12,0) -> 3 | C39: =G38 -> 173 | D39: =ROUND(IF(B39=1,Assumptions!$B$31,IF(B39=2,Assumptions!$B$32,Assumptions!$B$33))*MIN(1,A39/6),0) -> 15 | E39: =MAX(0,MIN(ROUND(D39*Assumptions!$B$29,0),Assumptions!$B$5-(C39-F39))) -> 9 | F39: =ROUND(C39*Assumptions!$B$30,0) -> 7 | G39: =MAX(0,MIN(Assumptions!$B$5,C39+E39-F39)) -> 175 | H39: =C39*Assumptions!$B$28 -> 2595000 | I39: =E39*Assumptions!$B$6 -> 270000 | J39: =D39*Assumptions!$B$7 -> 30000 | K39: =C39*Assumptions!$B$37 -> 346000 | L39: =SUM(H39:K39) -> 3241000 | M39: =K39*Assumptions!$B$8 -> 224900 | N39: =L39*Assumptions!$B$9*Assumptions!$B$10 -> 87507 | O39: =M39+N39 -> 312407 | P39: =Assumptions!$B$13 -> 400000 | Q39: =Assumptions!$B$36 -> 580000 | R39: =IF(A39<=3,Assumptions!$B$34,Assumptions!$B$35) -> 50000 | S39: =Assumptions!$B$44 -> 187460 | T39: =P39+Q39+R39+S39 -> 1217460 | U39: =(CAPEX!$B$18+CAPEX!$B$20)/(Assumptions!$B$11*12)+IF(A39>=Assumptions!$B$51,Assumptions!$B$50/(Assumptions!$B$11*12),0) -> 123273.81 | V39: =L39-O39-T39-U39 -> 1587859.2 | W39: =V39 -> 1587859.2 | X39: =MAX(0,W39)*Assumptions!$B$12 -> 476357.76 | Y39: =W39-X39 -> 1111501.4

Sheet Cash_Flow
A1: 月次キャッシュフロー
A2: 期末現金がマイナス＝資金ショート（赤表示）。営業CF=税引後利益+減価償却。
A3: 月 | B3: 営業CF | C3: 投資CF | D3: 財務CF | E3: 前受けCF(運転資本) | F3: 純増減 | G3: 期末現金 | H3: 累計営業CF | I3: 回収判定(内部)
A4: 0 | B4: 0 | C4: =-CAPEX!$B$21 -> -12355000 | D4: =Assumptions!$B$24+Assumptions!$B$25 -> 15000000 | E4: 0 | F4: =B4+C4+D4+E4 -> 2645000 | G4: =F4 -> 2645000 | H4: 0 | I4: 9999
A5: 1 | B5: =Monthly_PL!$Y4+Monthly_PL!$U4 -> -746012 | C5: =IF(A5=Assumptions!$B$51,-Assumptions!$B$50,0) -> 0 | D5: 0 | E5: =Assumptions!$B$47*Assumptions!$B$48*Assumptions!$B$28*(Monthly_PL!$G$4-0) -> 697500 | F5: =B5+C5+D5+E5 -> -48512 | G5: =G4+F5 -> 2596488 | H5: =SUM($B$5:B5) -> -746012 | I5: =IF(H5>=CAPEX!$B$21,A5,9999) -> 9999
A6: 2 | B6: =Monthly_PL!$Y5+Monthly_PL!$U5 -> -697689 | C6: =IF(A6=Assumptions!$B$51,-Assumptions!$B$50,0) -> 0 | D6: 0 | E6: =Assumptions!$B$47*Assumptions!$B$48*Assumptions!$B$28*(Monthly_PL!$G$5-Monthly_PL!$G$4) -> 45000 | F6: =B6+C6+D6+E6 -> -652689 | G6: =G5+F6 -> 1943799 | H6: =SUM($B$5:B6) -> -1443701 | I6: =IF(H6>=CAPEX!$B$21,A6,9999) -> 9999
A7: 3 | B7: =Monthly_PL!$Y6+Monthly_PL!$U6 -> -602989 | C7: =IF(A7=Assumptions!$B$51,-Assumptions!$B$50,0) -> 0 | D7: 0 | E7: =Assumptions!$B$47*Assumptions!$B$48*Assumptions!$B$28*(Monthly_PL!$G$6-Monthly_PL!$G$5) -> 90000 | F7: =B7+C7+D7+E7 -> -512989 | G7: =G6+F7 -> 1430810 | H7: =SUM($B$5:B7) -> -2046690 | I7: =IF(H7>=CAPEX!$B$21,A7,9999) -> 9999
A8: 4 | B8: =Monthly_PL!$Y7+Monthly_PL!$U7 -> -458943 | C8: =IF(A8=Assumptions!$B$51,-Assumptions!$B$50,0) -> 0 | D8: 0 | E8: =Assumptions!$B$47*Assumptions!$B$48*Assumptions!$B$28*(Monthly_PL!$G$7-Monthly_PL!$G$6) -> 112500 | F8: =B8+C8+D8+E8 -> -346443 | G8: =G7+F8 -> 1084367 | H8: =SUM($B$5:B8) -> -2505633 | I8: =IF(H8>=CAPEX!$B$21,A8,9999) -> 9999
A9: 5 | B9: =Monthly_PL!$Y8+Monthly_PL!$U8 -> -318520 | C9: =IF(A9=Assumptions!$B$51,-Assumptions!$B$50,0) -> 0 | D9: 0 | E9: =Assumptions!$B$47*Assumptions!$B$48*Assumptions!$B$28*(Monthly_PL!$G$8-Monthly_PL!$G$7) -> 135000 | F9: =B9+C9+D9+E9 -> -183520 | G9: =G8+F9 -> 900847 | H9: =SUM($B$5:B9) -> -2824153 | I9: =IF(H9>=CAPEX!$B$21,A9,9999) -> 9999
A10: 6 | B10: =Monthly_PL!$Y9+Monthly_PL!$U9 -> -193992 | C10: =IF(A10=Assumptions!$B$51,-Assumptions!$B$50,0) -> -400000 | D10: 0 | E10: =Assumptions!$B$47*Assumptions!$B$48*Assumptions!$B$28*(Monthly_PL!$G$9-Monthly_PL!$G$8) -> 157500 | F10: =B10+C10+D10+E10 -> -436492 | G10: =G9+F10 -> 464355 | H10: =SUM($B$5:B10) -> -3018145 | I10: =IF(H10>=CAPEX!$B$21,A10,9999) -> 9999
A11: 7 | B11: =Monthly_PL!$Y10+Monthly_PL!$U10 -> -87305 | C11: =IF(A11=Assumptions!$B$51,-Assumptions!$B$50,0) -> 0 | D11: 0 | E11: =Assumptions!$B$47*Assumptions!$B$48*Assumptions!$B$28*(Monthly_PL!$G$10-Monthly_PL!$G$9) -> 157500 | F11: =B11+C11+D11+E11 -> 70195 | G11: =G10+F11 -> 534550 | H11: =SUM($B$5:B11) -> -3105450 | I11: =IF(H11>=CAPEX!$B$21,A11,9999) -> 9999
A12: 8 | B12: =Monthly_PL!$Y11+Monthly_PL!$U11 -> 19382 | C12: =IF(A12=Assumptions!$B$51,-Assumptions!$B$50,0) -> 0 | D12: 0 | E12: =Assumptions!$B$47*Assumptions!$B$48*Assumptions!$B$28*(Monthly_PL!$G$11-Monthly_PL!$G$10) -> 157500 | F12: =B12+C12+D12+E12 -> 176882 | G12: =G11+F12 -> 711432 | H12: =SUM($B$5:B12) -> -3086068 | I12: =IF(H12>=CAPEX!$B$21,A12,9999) -> 9999
A13: 9 | B13: =Monthly_PL!$Y12+Monthly_PL!$U12 -> 125230.44 | C13: =IF(A13=Assumptions!$B$51,-Assumptions!$B$50,0) -> 0 | D13: 0 | E13: =Assumptions!$B$47*Assumptions!$B$48*Assumptions!$B$28*(Monthly_PL!$G$12-Monthly_PL!$G$11) -> 135000 | F13: =B13+C13+D13+E13 -> 260230.44 | G13: =G12+F13 -> 971662.44 | H13: =SUM($B$5:B13) -> -2960837.6 | I13: =IF(H13>=CAPEX!$B$21,A13,9999) -> 9999
A14: 10 | B14: =Monthly_PL!$Y13+Monthly_PL!$U13 -> 189242.64 | C14: =IF(A14=Assumptions!$B$51,-Assumptions!$B$50,0) -> 0 | D14: 0 | E14: =Assumptions!$B$47*Assumptions!$B$48*Assumptions!$B$28*(Monthly_PL!$G$13-Monthly_PL!$G$12) -> 135000 | F14: =B14+C14+D14+E14 -> 324242.64 | G14: =G13+F14 -> 1295905.1 | H14: =SUM($B$5:B14) -> -2771594.9 | I14: =IF(H14>=CAPEX!$B$21,A14,9999) -> 9999
A15: 11 | B15: =Monthly_PL!$Y14+Monthly_PL!$U14 -> 253254.84 | C15: =IF(A15=Assumptions!$B$51,-Assumptions!$B$50,0) -> 0 | D15: 0 | E15: =Assumptions!$B$47*Assumptions!$B$48*Assumptions!$B$28*(Monthly_PL!$G$14-Monthly_PL!$G$13) -> 135000 | F15: =B15+C15+D15+E15 -> 388254.84 | G15: =G14+F15 -> 1684159.9 | H15: =SUM($B$5:B15) -> -2518340.1 | I15: =IF(H15>=CAPEX!$B$21,A15,9999) -> 9999
A16: 12 | B16: =Monthly_PL!$Y15+Monthly_PL!$U15 -> 317267.04 | C16: =IF(A16=Assumptions!$B$51,-Assumptions!$B$50,0) -> 0 | D16: 0 | E16: =Assumptions!$B$47*Assumptions!$B$48*Assumptions!$B$28*(Monthly_PL!$G$15-Monthly_PL!$G$14) -> 135000 | F16: =B16+C16+D16+E16 -> 452267.04 | G16: =G15+F16 -> 2136427 | H16: =SUM($B$5:B16) -> -2201073 | I16: =IF(H16>=CAPEX!$B$21,A16,9999) -> 9999
A17: 13 | B17: =Monthly_PL!$Y16+Monthly_PL!$U16 -> 381279.24 | C17: =IF(A17=Assumptions!$B$51,-Assumptions!$B$50,0) -> 0 | D17: 0 | E17: =Assumptions!$B$47*Assumptions!$B$48*Assumptions!$B$28*(Monthly_PL!$G$16-Monthly_PL!$G$15) -> 112500 | F17: =B17+C17+D17+E17 -> 493779.24 | G17: =G16+F17 -> 2630206.2 | H17: =SUM($B$5:B17) -> -1819793.8 | I17: =IF(H17>=CAPEX!$B$21,A17,9999) -> 9999
A18: 14 | B18: =Monthly_PL!$Y17+Monthly_PL!$U17 -> 434622.74 | C18: =IF(A18=Assumptions!$B$51,-Assumptions!$B$50,0) -> 0 | D18: 0 | E18: =Assumptions!$B$47*Assumptions!$B$48*Assumptions!$B$28*(Monthly_PL!$G$17-Monthly_PL!$G$16) -> 112500 | F18: =B18+C18+D18+E18 -> 547122.74 | G18: =G17+F18 -> 3177329 | H18: =SUM($B$5:B18) -> -1385171 | I18: =IF(H18>=CAPEX!$B$21,A18,9999) -> 9999
A19: 15 | B19: =Monthly_PL!$Y18+Monthly_PL!$U18 -> 487966.24 | C19: =IF(A19=Assumptions!$B$51,-Assumptions!$B$50,0) -> 0 | D19: 0 | E19: =Assumptions!$B$47*Assumptions!$B$48*Assumptions!$B$28*(Monthly_PL!$G$18-Monthly_PL!$G$17) -> 112500 | F19: =B19+C19+D19+E19 -> 600466.24 | G19: =G18+F19 -> 3777795.2 | H19: =SUM($B$5:B19) -> -897204.8 | I19: =IF(H19>=CAPEX!$B$21,A19,9999) -> 9999
A20: 16 | B20: =Monthly_PL!$Y19+Monthly_PL!$U19 -> 541309.74 | C20: =IF(A20=Assumptions!$B$51,-Assumptions!$B$50,0) -> 0 | D20: 0 | E20: =Assumptions!$B$47*Assumptions!$B$48*Assumptions!$B$28*(Monthly_PL!$G$19-Monthly_PL!$G$18) -> 112500 | F20: =B20+C20+D20+E20 -> 653809.74 | G20: =G19+F20 -> 4431604.9 | H20: =SUM($B$5:B20) -> -355895.06 | I20: =IF(H20>=CAPEX!$B$21,A20,9999) -> 9999
A21: 17 | B21: =Monthly_PL!$Y20+Monthly_PL!$U20 -> 594653.24 | C21: =IF(A21=Assumptions!$B$51,-Assumptions!$B$50,0) -> 0 | D21: 0 | E21: =Assumptions!$B$47*Assumptions!$B$48*Assumptions!$B$28*(Monthly_PL!$G$20-Monthly_PL!$G$19) -> 90000 | F21: =B21+C21+D21+E21 -> 684653.24 | G21: =G20+F21 -> 5116258.2 | H21: =SUM($B$5:B21) -> 238758.19 | I21: =IF(H21>=CAPEX!$B$21,A21,9999) -> 9999
A22: 18 | B22: =Monthly_PL!$Y21+Monthly_PL!$U21 -> 637328.04 | C22: =IF(A22=Assumptions!$B$51,-Assumptions!$B$50,0) -> 0 | D22: 0 | E22: =Assumptions!$B$47*Assumptions!$B$48*Assumptions!$B$28*(Monthly_PL!$G$21-Monthly_PL!$G$20) -> 90000 | F22: =B22+C22+D22+E22 -> 727328.04 | G22: =G21+F22 -> 5843586.2 | H22: =SUM($B$5:B22) -> 876086.23 | I22: =IF(H22>=CAPEX!$B$21,A22,9999) -> 9999
A23: 19 | B23: =Monthly_PL!$Y22+Monthly_PL!$U22 -> 680002.84 | C23: =IF(A23=Assumptions!$B$51,-Assumptions!$B$50,0) -> 0 | D23: 0 | E23: =Assumptions!$B$47*Assumptions!$B$48*Assumptions!$B$28*(Monthly_PL!$G$22-Monthly_PL!$G$21) -> 90000 | F23: =B23+C23+D23+E23 -> 770002.84 | G23: =G22+F23 -> 6613589.1 | H23: =SUM($B$5:B23) -> 1556089.1 | I23: =IF(H23>=CAPEX!$B$21,A23,9999) -> 9999
A24: 20 | B24: =Monthly_PL!$Y23+Monthly_PL!$U23 -> 722677.64 | C24: =IF(A24=Assumptions!$B$51,-Assumptions!$B$50,0) -> 0 | D24: 0 | E24: =Assumptions!$B$47*Assumptions!$B$48*Assumptions!$B$28*(Monthly_PL!$G$23-Monthly_PL!$G$22) -> 90000 | F24: =B24+C24+D24+E24 -> 812677.64 | G24: =G23+F24 -> 7426266.7 | H24: =SUM($B$5:B24) -> 2278766.7 | I24: =IF(H24>=CAPEX!$B$21,A24,9999) -> 9999
A25: 21 | B25: =Monthly_PL!$Y24+Monthly_PL!$U24 -> 765352.44 | C25: =IF(A25=Assumptions!$B$51,-Assumptions!$B$50,0) -> 0 | D25: 0 | E25: =Assumptions!$B$47*Assumptions!$B$48*Assumptions!$B$28*(Monthly_PL!$G$24-Monthly_PL!$G$23) -> 90000 | F25: =B25+C25+D25+E25 -> 855352.44 | G25: =G24+F25 -> 8281619.2 | H25: =SUM($B$5:B25) -> 3044119.2 | I25: =IF(H25>=CAPEX!$B$21,A25,9999) -> 9999
A26: 22 | B26: =Monthly_PL!$Y25+Monthly_PL!$U25 -> 808027.24 | C26: =IF(A26=Assumptions!$B$51,-Assumptions!$B$50,0) -> 0 | D26: 0 | E26: =Assumptions!$B$47*Assumptions!$B$48*Assumptions!$B$28*(Monthly_PL!$G$25-Monthly_PL!$G$24) -> 90000 | F26: =B26+C26+D26+E26 -> 898027.24 | G26: =G25+F26 -> 9179646.4 | H26: =SUM($B$5:B26) -> 3852146.4 | I26: =IF(H26>=CAPEX!$B$21,A26,9999) -> 9999
A27: 23 | B27: =Monthly_PL!$Y26+Monthly_PL!$U26 -> 850702.04 | C27: =IF(A27=Assumptions!$B$51,-Assumptions!$B$50,0) -> 0 | D27: 0 | E27: =Assumptions!$B$47*Assumptions!$B$48*Assumptions!$B$28*(Monthly_PL!$G$26-Monthly_PL!$G$25) -> 90000 | F27: =B27+C27+D27+E27 -> 940702.04 | G27: =G26+F27 -> 10120348 | H27: =SUM($B$5:B27) -> 4702848.4 | I27: =IF(H27>=CAPEX!$B$21,A27,9999) -> 9999
A28: 24 | B28: =Monthly_PL!$Y27+Monthly_PL!$U27 -> 893376.84 | C28: =IF(A28=Assumptions!$B$51,-Assumptions!$B$50,0) -> 0 | D28: 0 | E28: =Assumptions!$B$47*Assumptions!$B$48*Assumptions!$B$28*(Monthly_PL!$G$27-Monthly_PL!$G$26) -> 67500 | F28: =B28+C28+D28+E28 -> 960876.84 | G28: =G27+F28 -> 11081225 | H28: =SUM($B$5:B28) -> 5596225.3 | I28: =IF(H28>=CAPEX!$B$21,A28,9999) -> 9999
A29: 25 | B29: =Monthly_PL!$Y28+Monthly_PL!$U28 -> 925382.94 | C29: =IF(A29=Assumptions!$B$51,-Assumptions!$B$50,0) -> 0 | D29: 0 | E29: =Assumptions!$B$47*Assumptions!$B$48*Assumptions!$B$28*(Monthly_PL!$G$28-Monthly_PL!$G$27) -> 67500 | F29: =B29+C29+D29+E29 -> 992882.94 | G29: =G28+F29 -> 12074108 | H29: =SUM($B$5:B29) -> 6521608.2 | I29: =IF(H29>=CAPEX!$B$21,A29,9999) -> 9999
A30: 26 | B30: =Monthly_PL!$Y29+Monthly_PL!$U29 -> 957389.04 | C30: =IF(A30=Assumptions!$B$51,-Assumptions!$B$50,0) -> 0 | D30: 0 | E30: =Assumptions!$B$47*Assumptions!$B$48*Assumptions!$B$28*(Monthly_PL!$G$29-Monthly_PL!$G$28) -> 67500 | F30: =B30+C30+D30+E30 -> 1024889 | G30: =G29+F30 -> 13098997 | H30: =SUM($B$5:B30) -> 7478997.3 | I30: =IF(H30>=CAPEX!$B$21,A30,9999) -> 9999
A31: 27 | B31: =Monthly_PL!$Y30+Monthly_PL!$U30 -> 989395.14 | C31: =IF(A31=Assumptions!$B$51,-Assumptions!$B$50,0) -> 0 | D31: 0 | E31: =Assumptions!$B$47*Assumptions!$B$48*Assumptions!$B$28*(Monthly_PL!$G$30-Monthly_PL!$G$29) -> 67500 | F31: =B31+C31+D31+E31 -> 1056895.1 | G31: =G30+F31 -> 14155892 | H31: =SUM($B$5:B31) -> 8468392.4 | I31: =IF(H31>=CAPEX!$B$21,A31,9999) -> 9999
A32: 28 | B32: =Monthly_PL!$Y31+Monthly_PL!$U31 -> 1021401.2 | C32: =IF(A32=Assumptions!$B$51,-Assumptions!$B$50,0) -> 0 | D32: 0 | E32: =Assumptions!$B$47*Assumptions!$B$48*Assumptions!$B$28*(Monthly_PL!$G$31-Monthly_PL!$G$30) -> 67500 | F32: =B32+C32+D32+E32 -> 1088901.2 | G32: =G31+F32 -> 15244794 | H32: =SUM($B$5:B32) -> 9489793.7 | I32: =IF(H32>=CAPEX!$B$21,A32,9999) -> 9999
A33: 29 | B33: =Monthly_PL!$Y32+Monthly_PL!$U32 -> 1053407.3 | C33: =IF(A33=Assumptions!$B$51,-Assumptions!$B$50,0) -> 0 | D33: 0 | E33: =Assumptions!$B$47*Assumptions!$B$48*Assumptions!$B$28*(Monthly_PL!$G$32-Monthly_PL!$G$31) -> 67500 | F33: =B33+C33+D33+E33 -> 1120907.3 | G33: =G32+F33 -> 16365701 | H33: =SUM($B$5:B33) -> 10543201 | I33: =IF(H33>=CAPEX!$B$21,A33,9999) -> 9999
A34: 30 | B34: =Monthly_PL!$Y33+Monthly_PL!$U33 -> 1085413.4 | C34: =IF(A34=Assumptions!$B$51,-Assumptions!$B$50,0) -> 0 | D34: 0 | E34: =Assumptions!$B$47*Assumptions!$B$48*Assumptions!$B$28*(Monthly_PL!$G$33-Monthly_PL!$G$32) -> 67500 | F34: =B34+C34+D34+E34 -> 1152913.4 | G34: =G33+F34 -> 17518614 | H34: =SUM($B$5:B34) -> 11628614 | I34: =IF(H34>=CAPEX!$B$21,A34,9999) -> 9999
A35: 31 | B35: =Monthly_PL!$Y34+Monthly_PL!$U34 -> 1117419.5 | C35: =IF(A35=Assumptions!$B$51,-Assumptions!$B$50,0) -> 0 | D35: 0 | E35: =Assumptions!$B$47*Assumptions!$B$48*Assumptions!$B$28*(Monthly_PL!$G$34-Monthly_PL!$G$33) -> 67500 | F35: =B35+C35+D35+E35 -> 1184919.5 | G35: =G34+F35 -> 18703534 | H35: =SUM($B$5:B35) -> 12746034 | I35: =IF(H35>=CAPEX!$B$21,A35,9999) -> 31
A36: 32 | B36: =Monthly_PL!$Y35+Monthly_PL!$U35 -> 1149425.6 | C36: =IF(A36=Assumptions!$B$51,-Assumptions!$B$50,0) -> 0 | D36: 0 | E36: =Assumptions!$B$47*Assumptions!$B$48*Assumptions!$B$28*(Monthly_PL!$G$35-Monthly_PL!$G$34) -> 45000 | F36: =B36+C36+D36+E36 -> 1194425.6 | G36: =G35+F36 -> 19897960 | H36: =SUM($B$5:B36) -> 13895460 | I36: =IF(H36>=CAPEX!$B$21,A36,9999) -> 32
A37: 33 | B37: =Monthly_PL!$Y36+Monthly_PL!$U36 -> 1170763 | C37: =IF(A37=Assumptions!$B$51,-Assumptions!$B$50,0) -> 0 | D37: 0 | E37: =Assumptions!$B$47*Assumptions!$B$48*Assumptions!$B$28*(Monthly_PL!$G$36-Monthly_PL!$G$35) -> 45000 | F37: =B37+C37+D37+E37 -> 1215763 | G37: =G36+F37 -> 21113723 | H37: =SUM($B$5:B37) -> 15066223 | I37: =IF(H37>=CAPEX!$B$21,A37,9999) -> 33
A38: 34 | B38: =Monthly_PL!$Y37+Monthly_PL!$U37 -> 1192100.4 | C38: =IF(A38=Assumptions!$B$51,-Assumptions!$B$50,0) -> 0 | D38: 0 | E38: =Assumptions!$B$47*Assumptions!$B$48*Assumptions!$B$28*(Monthly_PL!$G$37-Monthly_PL!$G$36) -> 45000 | F38: =B38+C38+D38+E38 -> 1237100.4 | G38: =G37+F38 -> 22350823 | H38: =SUM($B$5:B38) -> 16258323 | I38: =IF(H38>=CAPEX!$B$21,A38,9999) -> 34
A39: 35 | B39: =Monthly_PL!$Y38+Monthly_PL!$U38 -> 1213437.8 | C39: =IF(A39=Assumptions!$B$51,-Assumptions!$B$50,0) -> 0 | D39: 0 | E39: =Assumptions!$B$47*Assumptions!$B$48*Assumptions!$B$28*(Monthly_PL!$G$38-Monthly_PL!$G$37) -> 45000 | F39: =B39+C39+D39+E39 -> 1258437.8 | G39: =G38+F39 -> 23609261 | H39: =SUM($B$5:B39) -> 17471761 | I39: =IF(H39>=CAPEX!$B$21,A39,9999) -> 35
A40: 36 | B40: =Monthly_PL!$Y39+Monthly_PL!$U39 -> 1234775.2 | C40: =IF(A40=Assumptions!$B$51,-Assumptions!$B$50,0) -> 0 | D40: 0 | E40: =Assumptions!$B$47*Assumptions!$B$48*Assumptions!$B$28*(Monthly_PL!$G$39-Monthly_PL!$G$38) -> 45000 | F40: =B40+C40+D40+E40 -> 1279775.2 | G40: =G39+F40 -> 24889036 | H40: =SUM($B$5:B40) -> 18706536 | I40: =IF(H40>=CAPEX!$B$21,A40,9999) -> 36

Sheet BreakEven
A1: 損益分岐点分析
A2: 月固定費(定常/Y2-3) | B2: =Assumptions!$B$13+Assumptions!$B$36+Assumptions!$B$35+Assumptions!$B$44 -> 1217460
A3: 平均月会費(税抜) | B3: =Assumptions!$B$28 -> 15000
A4: 物販ARPU | B4: =Assumptions!$B$37 -> 2000
A5: 物販原価率 | B5: =Assumptions!$B$8 -> 0.65
A6: 決済実効率(手数料率×適用率) | B6: =Assumptions!$B$9*Assumptions!$B$10 -> 0.027
A7: 会員あたり月次貢献 | B7: =B3*(1-B6)+B4*(1-B5)-B4*B6 -> 15241
A8: 損益分岐点 会員数 | B8: =ROUNDUP(B2/B7,0) -> 80
A9: 必要月商(概算) | B9: =B8*(B3+B4) -> 1360000
A10: 現状会員(36ヶ月) | B10: =Monthly_PL!$G$39 -> 175
A11: BEP-現状会員 差 | B11: =B8-B10 -> -95
A12: BEP維持に必要な月間入会(退会補填) | B12: =ROUNDUP(B8*Assumptions!$B$30,0) -> 4
A13: 必要月間体験数 | B13: =ROUNDUP(B11/Assumptions!$B$29,0) -> -159

Sheet Sensitivity
A1: 感応度分析（年間営業利益への影響・一次近似）
A2: 精緻な再計算はAssumptionsを変更しSummaryで確認。下表は目安。
A4: 基準:年間営業利益(Y3/25-36月) | B4: =SUM(Monthly_PL!$V$28:$V$39) -> 16615750
A6: 変動要因 | B6: 変化幅 | C6: 年間営業利益への影響(近似)
A7: 会員数 | B7: +10% | C7: =0.1*Monthly_PL!$G$39*BreakEven!$B$7*12 -> 3200610
A8: 会員数 | B8: -10% | C8: =-0.1*Monthly_PL!$G$39*BreakEven!$B$7*12 -> -3200610
A9: 平均月会費 | B9: +1,000円 | C9: =Monthly_PL!$G$39*1000*(1-Assumptions!$B$9*Assumptions!$B$10)*12 -> 2043300
A10: 平均月会費 | B10: -1,000円 | C10: =-Monthly_PL!$G$39*1000*(1-Assumptions!$B$9*Assumptions!$B$10)*12 -> -2043300
A11: 退会率 | B11: +2pt | C11: =-Monthly_PL!$G$39*0.02*BreakEven!$B$7*12 -> -640122
A12: 広告費 | B12: +20% | C12: =-Assumptions!$B$35*0.2*12 -> -120000
A13: 人件費 | B13: +10% | C13: =-Assumptions!$B$36*0.1*12 -> -696000
A14: 家賃 | B14: +10% | C14: =-Assumptions!$B$13*0.1*12 -> -480000

Sheet Risks
A1: リスク一覧（影響度・発生可能性・対策）
A3: 分類 | B3: リスク | C3: 影響度 | D3: 発生可能性 | E3: 対策
A4: 出店 | B4: 良物件が出ない/賃料高 | C4: 高 | D4: 中 | E4: 探索チャネル複数化・居抜き優先・条件緩和
A5: 集客 | B5: 初年度の会員立ち上がり遅延 | C5: 高 | D5: 高 | E5: 先行入会・紹介・体験導線一本化・広告前倒し
A6: 集客 | B6: 入会率が想定を下回る | C6: 高 | D6: 中 | E6: 体験の質・接客標準化・フォロー導線
A7: 運営 | B7: 退会率上昇(定着不足) | C7: 高 | D7: 中 | E7: 予約取りやすさ改善・レッスン価値・休会提案
A8: 資金繰り | B8: 初期投資超過で運転資金枯渇 | C8: 高 | D8: 高 | E8: CAPEX圧縮(段階投資)・追加融資枠・出資増額
A9: 資金繰り | B9: 資金ショート月の発生 | C9: 高 | D9: 中 | E9: 固定費の変動費化・支払サイト調整・与信枠
A10: 人材 | B10: 採用難/教育不足 | C10: 中 | D10: 中 | E10: 無人化比率UP・宝塚応援・動画教材
A11: 設備 | B11: シミュレーター故障/納期 | C11: 中 | D11: 中 | E11: 保守契約・予備部材・中位機で先行開業
A12: 法務 | B12: ブランド/名称使用の条件相違 | C12: 高 | D12: 中 | E12: ファインと書面合意(確認事項参照)
A13: 契約 | B13: 賃貸/原状回復/中途解約の負担 | C13: 中 | D13: 中 | E13: 契約前の条件精査・弁護士確認
A14: 近隣 | B14: 騒音クレーム | C14: 中 | D14: 低 | E14: 事前騒音測定・防音余裕設計
A15: ブランド | B15: 運営品質のばらつきでGOLF WING毀損 | C15: 高 | D15: 中 | E15: SOP整備・KPI監視・是正フロー

Sheet Investor_QA
A1: 想定問答（ファイン/金融機関/出資者）
A3: 想定質問 | B3: 回答案
A4: 売上前提は過大では? | B4: 宝塚の加重平均会費18,800円を15,000円へ保守補正。入会率も純転換のみ採用。悲観/最悪で退会率6-8%を検証。
A5: 初期投資は足りるか? | B5: 既存楽観案は保証金・予備費・開業前費用が未計上。本モデルで保守計上した結果、総初期投資は出資1,500万を上回り得るため、CAPEX圧縮or追加調達を明示。
A6: 資金ショートは? | B6: Cash_Flowで月末現金を可視化。標準では回避、悲観/最悪では発生月を赤表示。対策(段階投資/融資枠)を用意。
A7: 投資回収は? | B7: Summaryに投資回収月を表示。標準で概ね2-3年目、悲観で長期化。
A8: 集客が失敗したら? | B8: 最悪シナリオで初期集客失敗・退会増・広告増・人件費増・修繕発生を同時反映し耐性を確認。
A9: 損益分岐点は? | B9: BreakEvenで会員数・必要月商・必要体験数を提示。定常固定費÷会員貢献。
A10: ファインとの関係は? | B10: 名称・ブランド・システム利用の範囲と責任分担を書面合意(確認事項一覧)。
A11: 人が採れなかったら? | B11: 無人運営モデルで必要人員を圧縮。宝塚からの応援と業務委託で補完。
A12: 競合が増えたら? | B12: 会員制+レッスン+無人+システム化で差別化。KPI監視で早期対応。
A13: 撤退基準は? | B13: 一定期間の会員数/現金残高が基準割れで段階縮小・撤退を事前定義(要協議)。
