Workbook

Sheet Summary
A1: GOLF WING 2号店 収支サマリー
A2: 選択シナリオ: | B2: =Scenarios!$B$2 -> 標準 | D2: 打席数・坪数はAssumptionsで変更
A4: ■ 店舗規模
A5: 打席数 | B5: =Assumptions!$B$5 -> 4
A6: 坪数 | B6: =Assumptions!$B$6 -> 48
A7: 会員上限 | B7: =Assumptions!$B$31 -> 180
A9: ■ 資金
A10: 総初期投資 | B10: =CAPEX!$B$21 -> 32386000
A11: うち内装工事 | B11: =CAPEX!$B$5 -> 14400000
A12: うち機材 | B12: =CAPEX!$B$9 -> 5200000
A13: 出資金 | B13: =Assumptions!$B$28 -> 20000000
A14: 自己資金・融資 | B14: =Assumptions!$B$29 -> 0
A15: 開業時運転資金 | B15: =Assumptions!$B$28+Assumptions!$B$29-CAPEX!$B$21 -> -12386000
A16: 最低現金残高 | B16: =MIN(Cash_Flow!$G$4:$G$40) -> -18580103
A17: 資金ショート月数 | B17: =COUNTIF(Cash_Flow!$G$5:$G$40,"<0") -> 30
A18: 投資回収期間(月) | B18: =IF(MIN(Cash_Flow!$I$5:$I$40)=9999,"36ヶ月内未回収",MIN(Cash_Flow!$I$5:$I$40)) -> 36ヶ月内未回収
A20: ■ 損益(年次)
A21: 指標 | B21: Y1 | C21: Y2 | D21: Y3 | E21: 36ヶ月累計
A22: 売上高 | B22: =SUM(Monthly_PL!$L$4:$L$15) -> 15247400 | C22: =SUM(Monthly_PL!$L$16:$L$27) -> 35593800 | D22: =SUM(Monthly_PL!$L$28:$L$39) -> 45390900 | E22: =SUM(Monthly_PL!$L$4:$L$39) -> 96232100
A23: 営業利益 | B23: =SUM(Monthly_PL!$V$4:$V$15) -> -11489238 | C23: =SUM(Monthly_PL!$V$16:$V$27) -> 6994267.4 | D23: =SUM(Monthly_PL!$V$28:$V$39) -> 15589221 | E23: =SUM(Monthly_PL!$V$4:$V$39) -> 11094250
A24: 税引後利益 | B24: =SUM(Monthly_PL!$Y$4:$Y$15) -> -11489238 | C24: =SUM(Monthly_PL!$Y$16:$Y$27) -> 4861794.4 | D24: =SUM(Monthly_PL!$Y$28:$Y$39) -> 10912454 | E24: =SUM(Monthly_PL!$Y$4:$Y$39) -> 4285010.8
A26: ■ 主要指標
A27: 期末会員数(36ヶ月) | B27: =Monthly_PL!$G$39 -> 180
A28: 損益分岐点会員数 | B28: =BreakEven!$B$8 -> 103
A29: 現状-BEP会員差 | B29: =Monthly_PL!$G$39-BreakEven!$B$8 -> 77
A32: 注: 非居抜き前提の仮置き初版。物件条件確定で更新。

Sheet Scenarios
A1: シナリオ設定（4パターン）
A2: 選択シナリオ → | B2: 標準 | D2: B2で全シート自動更新
A4: パラメータ | B4: 楽観 | C4: 標準 | D4: 悲観 | E4: 最悪 | F4: 選択中(自動) | G4: 備考
A5: 平均月会費(税抜) | B5: 18500 | C5: 17000 | D5: 15500 | E5: 14000 | F5: =INDEX(B5:E5,MATCH($B$2,$B$4:$E$4,0)) -> 17000 | G5: 8月値上げ後(レギュラー19,800/マスター24,800等)の加重平均を保守補正
A6: 入会率(体験→入会) | B6: 0.65 | C6: 0.55 | D6: 0.35 | E6: 0.25 | F6: =INDEX(B6:E6,MATCH($B$2,$B$4:$E$4,0)) -> 0.55 | G6: 宝塚の高転換を参考に保守設定
A7: 退会率(月次) | B7: 0.03 | C7: 0.04 | D7: 0.06 | E7: 0.08 | F7: =INDEX(B7:E7,MATCH($B$2,$B$4:$E$4,0)) -> 0.04 | G7: 相互利用で定着改善を見込むが保守
A8: 月間体験数 Y1 | B8: 22 | C8: 16 | D8: 10 | E8: 6 | F8: =INDEX(B8:E8,MATCH($B$2,$B$4:$E$4,0)) -> 16 | G8: 初年度
A9: 月間体験数 Y2 | B9: 30 | C9: 22 | D9: 14 | E9: 9 | F9: =INDEX(B9:E9,MATCH($B$2,$B$4:$E$4,0)) -> 22
A10: 月間体験数 Y3 | B10: 36 | C10: 26 | D10: 18 | E10: 11 | F10: =INDEX(B10:E10,MATCH($B$2,$B$4:$E$4,0)) -> 26
A11: 広告費 開業1-3ヶ月(月) | B11: 150000 | C11: 180000 | D11: 220000 | E11: 280000 | F11: =INDEX(B11:E11,MATCH($B$2,$B$4:$E$4,0)) -> 180000 | G11: 大型店の開業集客
A12: 広告費 4ヶ月目以降(月) | B12: 80000 | C12: 100000 | D12: 130000 | E12: 170000 | F12: =INDEX(B12:E12,MATCH($B$2,$B$4:$E$4,0)) -> 100000
A13: 人件費(月) | B13: 700000 | C13: 850000 | D13: 1000000 | E13: 1200000 | F13: =INDEX(B13:E13,MATCH($B$2,$B$4:$E$4,0)) -> 850000 | G13: 3-5打席・一部有人。最悪は増員
A14: 物販ARPU(会員/月) | B14: 3500 | C14: 2500 | D14: 1800 | E14: 1200 | F14: =INDEX(B14:E14,MATCH($B$2,$B$4:$E$4,0)) -> 2500
A15: 開業時先行会員数 | B15: 40 | C15: 30 | D15: 12 | E15: 6 | F15: =INDEX(B15:E15,MATCH($B$2,$B$4:$E$4,0)) -> 30 | G15: 宝塚会員の相互利用移行含む
A16: 追加CAPEX(初期不良等) | B16: 0 | C16: 0 | D16: 500000 | E16: 1200000 | F16: =INDEX(B16:E16,MATCH($B$2,$B$4:$E$4,0)) -> 0 | G16: 悲観/最悪

Sheet Assumptions
A1: 前提条件（入力の集約）
A2: 黄=入力／緑=参照。打席数・坪数を変えると会員上限・内装・機材・家賃が自動連動
A4: ■ 店舗規模・基本前提
A5: 打席数 | B5: 4
A6: 坪数 | B6: 48
A7: 会員/打席(上限係数) | B7: 45
A8: 入会金(税抜) | B8: 30000
A9: 体験単価(税抜) | B9: 2200
A10: 物販原価率 | B10: 0.65
A11: 決済手数料率 | B11: 0.03
A12: 決済適用率 | B12: 0.9
A13: 減価償却年数(設備) | B13: 8
A14: 実効税率 | B14: 0.3
A15: 賃料坪単価(月) | B15: 12000
A16: 内装坪単価(非居抜き) | B16: 300000
... A29: 自己資金・融資 | B29: 0
A31: 会員上限(=打席×係数) | B31: =B5*B7 -> 180
A32: 家賃(=坪数×賃料坪単価) | B32: =B6*B15 -> 576000
A33: ■ 選択シナリオ反映値（自動）
A34: 平均月会費(税抜) | B34: =Scenarios!F5 -> 17000
A35: 入会率 | B35: =Scenarios!F6 -> 0.55
A36: 退会率(月) | B36: =Scenarios!F7 -> 0.04
A37: 月間体験数 Y1 | B37: =Scenarios!F8 -> 16
A38: 月間体験数 Y2 | B38: =Scenarios!F9 -> 22
A39: 月間体験数 Y3 | B39: =Scenarios!F10 -> 26
A40: 広告費 開業1-3ヶ月(月) | B40: =Scenarios!F11 -> 180000
A41: 広告費 4ヶ月目以降(月) | B41: =Scenarios!F12 -> 100000
A42: 人件費(月) | B42: =Scenarios!F13 -> 850000
A43: 物販ARPU(月) | B43: =Scenarios!F14 -> 2500
A44: 開業時先行会員数 | B44: =Scenarios!F15 -> 30
A45: 追加CAPEX | B45: =Scenarios!F16 -> 0
A47: その他固定費小計 | B47: =B18+B19+B20+B21+B22+B23+B24+B25 -> 250000
A48: 予備費 | B48: =B47*B26 -> 7500
A49: その他固定費 計 | B49: =B47+B48 -> 257500
A51: ■ 前受け（月会費先取り）
A52: 前受けON(1=有効,0=無効) | B52: 1
A53: 前受けフロート係数(月分) | B53: 1.5
A54: ■ 後日投資（防犯・セキュリティ）
A55: 防犯・セキュリティ投資額 | B55: 500000
A56: 実施月(開業何ヶ月後) | B56: 6

Sheet CAPEX
A1: 初期投資（CAPEX）内訳 ※非居抜き
A2: 内装=坪数×内装坪単価、機材=打席数×単価/打席 で自動連動。防犯は初期投資外(開業N ヶ月後)
A4: 項目 | B4: 金額 | C4: 備考
A5: 内装工事(非居抜き) | B5: =Assumptions!$B$6*Assumptions!$B$16 -> 14400000 | C5: 坪数×坪単価。スケルトンから造作・打席ブース
A6: 電気工事 | B6: 1200000 | C6: 分電盤・打席電源・照明
A7: 空調・換気・設備工事 | B7: 1500000 | C7: 大型・打席発熱対応
A8: 防音・安全対策 | B8: 1200000 | C8: 防音・防球・防護
A9: シミュレーター・機材 | B9: =Assumptions!$B$5*Assumptions!$B$17 -> 5200000 | C9: 打席数×単価/打席
A10: PC・ネットワーク・AV | B10: 700000
A11: 什器・備品 | B11: 700000
A12: 看板・サイン | B12: 500000
A13: 決済・POS環境 | B13: 200000
A14: HP制作・初期ブランディング | B14: 300000 | C14: YOZAN WEB
A15: 開業前費用(採用・研修・内覧) | B15: 400000
A16: 設備小計 | B16: =SUM(B5:B15) -> 26300000
A17: 予備費(10%) | B17: =B16*0.1 -> 2630000
A18: CAPEX計(減価償却対象) | B18: =B16+B17 -> 28930000
A19: 保証金・敷金 | B19: =Assumptions!$B$32*Assumptions!$B$27 -> 3456000
A20: 追加CAPEX(シナリオ) | B20: =Assumptions!$B$45 -> 0
A21: 総初期投資 | B21: =B18+B19+B20 -> 32386000

Sheet OPEX
A1: 月次コスト内訳（OPEX）
A3: 区分 | B3: 項目 | C3: 金額(月) | D3: 種別 | E3: 備考
A4: 固定費 | B4: 家賃(坪数×坪単価) | C4: =Assumptions!$B$32 -> 576000 | D4: 固定
A5: 固定費 | B5: 人件費 | C5: =Assumptions!$B$42 -> 850000 | D5: 固定(シナリオ)
A6: 固定費 | B6: 広告費(開業1-3ヶ月) | C6: =Assumptions!$B$40 -> 180000 | D6: 固定(期間変動) | E6: 開業直後
A7: 固定費 | B7: 広告費(4ヶ月〜) | C7: =Assumptions!$B$41 -> 100000 | D7: 固定(期間変動) | E7: 4ヶ月目以降
A8: 固定費 | B8: 光熱費 | C8: =Assumptions!$B$18 -> 120000 | D8: 固定
A9: 固定費 | B9: 通信費 | C9: =Assumptions!$B$19 -> 15000 | D9: 固定
A10: 固定費 | B10: 保険 | C10: =Assumptions!$B$20 -> 15000 | D10: 固定
A11: 固定費 | B11: システム費 | C11: =Assumptions!$B$21 -> 10000 | D11: 固定 | E11: 自社Genesis
A12: 固定費 | B12: 清掃費 | C12: =Assumptions!$B$22 -> 30000 | D12: 固定
A13: 固定費 | B13: 修繕・設備更新積立 | C13: =Assumptions!$B$23 -> 40000 | D13: 固定
A14: 固定費 | B14: 消耗品費 | C14: =Assumptions!$B$24 -> 20000 | D14: 固定
A15: 固定費 | B15: 税理士費用 | C15: =Assumptions!$B$25 -> 0 | D15: 固定 | E15: YOZAN税理士=0
A16: 固定費 | B16: 予備費 | C16: =Assumptions!$B$48 -> 7500 | D16: 固定
A17: 変動費 | B17: 決済手数料 | C17: 売上×3%×適用率 | D17: 変動 | E17: Monthly_PL
A18: 変動費 | B18: 物販原価 | C18: 物販売上×65% | D18: 変動 | E18: Monthly_PL

Sheet Monthly_PL
A1: 月次損益計画（36ヶ月）
A3: 月 | B3: 年 | C3: 期首会員 | D3: 体験数 | E3: 入会数 | F3: 退会数 | G3: 期末会員 | H3: 月会費売上 | I3: 入会金売上 | J3: 体験売上 | K3: 物販売上 | L3: 売上合計 | M3: 物販原価 | N3: 決済手数料 | O3: 変動費計 | P3: 家賃 | Q3: 人件費 | R3: 広告費 | S3: その他固定費 | T3: 固定費計 | U3: 減価償却 | V3: 営業利益 | W3: 税前利益 | X3: 法人税等 | Y3: 税引後利益
A4: 1 | B4: =ROUNDUP(A4/12,0) -> 1 | C4: =Assumptions!$B$44 -> 30 | D4: =ROUND(IF(B4=1,Assumptions!$B$37,IF(B4=2,Assumptions!$B$38,Assumptions!$B$39))*MIN(1,A4/6),0) -> 3 | E4: =MAX(0,MIN(ROUND(D4*Assumptions!$B$35,0),Assumptions!$B$31-(C4-F4))) -> 2 | F4: =ROUND(C4*Assumptions!$B$36,0) -> 1 | G4: =MAX(0,MIN(Assumptions!$B$31,C4+E4-F4)) -> 31 | H4: =C4*Assumptions!$B$34 -> 510000 | I4: =E4*Assumptions!$B$8 -> 60000 | J4: =D4*Assumptions!$B$9 -> 6600 | K4: =C4*Assumptions!$B$43 -> 75000 | L4: =SUM(H4:K4) -> 651600 | M4: =K4*Assumptions!$B$10 -> 48750 | N4: =L4*Assumptions!$B$11*Assumptions!$B$12 -> 17593.2 | O4: =M4+N4 -> 66343.2 | P4: =Assumptions!$B$32 -> 576000 | Q4: =Assumptions!$B$42 -> 850000 | R4: =IF(A4<=3,Assumptions!$B$40,Assumptions!$B$41) -> 180000 | S4: =Assumptions!$B$49 -> 257500 | T4: =P4+Q4+R4+S4 -> 1863500 | U4: =(CAPEX!$B$18+CAPEX!$B$20)/(Assumptions!$B$13*12)+IF(A4>=Assumptions!$B$56,Assumptions!$B$55/(Assumptions!$B$13*12),0) -> 301354.17 | V4: =L4-O4-T4-U4 -> -1579597.4 | W4: =V4 -> -1579597.4 | X4: =MAX(0,W4)*Assumptions!$B$14 -> 0 | Y4: =W4-X4 -> -1579597.4
A5: 2 | B5: =ROUNDUP(A5/12,0) -> 1 | C5: =G4 -> 31 | D5: =ROUND(IF(B5=1,Assumptions!$B$37,IF(B5=2,Assumptions!$B$38,Assumptions!$B$39))*MIN(1,A5/6),0) -> 5 | E5: =MAX(0,MIN(ROUND(D5*Assumptions!$B$35,0),Assumptions!$B$31-(C5-F5))) -> 3 | F5: =ROUND(C5*Assumptions!$B$36,0) -> 1 | G5: =MAX(0,MIN(Assumptions!$B$31,C5+E5-F5)) -> 33 | H5: =C5*Assumptions!$B$34 -> 527000 | I5: =E5*Assumptions!$B$8 -> 90000 | J5: =D5*Assumptions!$B$9 -> 11000 | K5: =C5*Assumptions!$B$43 -> 77500 | L5: =SUM(H5:K5) -> 705500 | M5: =K5*Assumptions!$B$10 -> 50375 | N5: =L5*Assumptions!$B$11*Assumptions!$B$12 -> 19048.5 | O5: =M5+N5 -> 69423.5 | P5: =Assumptions!$B$32 -> 576000 | Q5: =Assumptions!$B$42 -> 850000 | R5: =IF(A5<=3,Assumptions!$B$40,Assumptions!$B$41) -> 180000 | S5: =Assumptions!$B$49 -> 257500 | T5: =P5+Q5+R5+S5 -> 1863500 | U5: =(CAPEX!$B$18+CAPEX!$B$20)/(Assumptions!$B$13*12)+IF(A5>=Assumptions!$B$56,Assumptions!$B$55/(Assumptions!$B$13*12),0) -> 301354.17 | V5: =L5-O5-T5-U5 -> -1528777.7 | W5: =V5 -> -1528777.7 | X5: =MAX(0,W5)*Assumptions!$B$14 -> 0 | Y5: =W5-X5 -> -1528777.7
A6: 3 | B6: =ROUNDUP(A6/12,0) -> 1 | C6: =G5 -> 33 | D6: =ROUND(IF(B6=1,Assumptions!$B$37,IF(B6=2,Assumptions!$B$38,Assumptions!$B$39))*MIN(1,A6/6),0) -> 8 | E6: =MAX(0,MIN(ROUND(D6*Assumptions!$B$35,0),Assumptions!$B$31-(C6-F6))) -> 4 | F6: =ROUND(C6*Assumptions!$B$36,0) -> 1 | G6: =MAX(0,MIN(Assumptions!$B$31,C6+E6-F6)) -> 36 | H6: =C6*Assumptions!$B$34 -> 561000 | I6: =E6*Assumptions!$B$8 -> 120000 | J6: =D6*Assumptions!$B$9 -> 17600 | K6: =C6*Assumptions!$B$43 -> 82500 | L6: =SUM(H6:K6) -> 781100 | M6: =K6*Assumptions!$B$10 -> 53625 | N6: =L6*Assumptions!$B$11*Assumptions!$B$12 -> 21089.7 | O6: =M6+N6 -> 74714.7 | P6: =Assumptions!$B$32 -> 576000 | Q6: =Assumptions!$B$42 -> 850000 | R6: =IF(A6<=3,Assumptions!$B$40,Assumptions!$B$41) -> 180000 | S6: =Assumptions!$B$49 -> 257500 | T6: =P6+Q6+R6+S6 -> 1863500 | U6: =(CAPEX!$B$18+CAPEX!$B$20)/(Assumptions!$B$13*12)+IF(A6>=Assumptions!$B$56,Assumptions!$B$55/(Assumptions!$B$13*12),0) -> 301354.17 | V6: =L6-O6-T6-U6 -> -1458468.9 | W6: =V6 -> -1458468.9 | X6: =MAX(0,W6)*Assumptions!$B$14 -> 0 | Y6: =W6-X6 -> -1458468.9
A7: 4 | B7: =ROUNDUP(A7/12,0) -> 1 | C7: =G6 -> 36 | D7: =ROUND(IF(B7=1,Assumptions!$B$37,IF(B7=2,Assumptions!$B$38,Assumptions!$B$39))*MIN(1,A7/6),0) -> 11 | E7: =MAX(0,MIN(ROUND(D7*Assumptions!$B$35,0),Assumptions!$B$31-(C7-F7))) -> 6 | F7: =ROUND(C7*Assumptions!$B$36,0) -> 1 | G7: =MAX(0,MIN(Assumptions!$B$31,C7+E7-F7)) -> 41 | H7: =C7*Assumptions!$B$34 -> 612000 | I7: =E7*Assumptions!$B$8 -> 180000 | J7: =D7*Assumptions!$B$9 -> 24200 | K7: =C7*Assumptions!$B$43 -> 90000 | L7: =SUM(H7:K7) -> 906200 | M7: =K7*Assumptions!$B$10 -> 58500 | N7: =L7*Assumptions!$B$11*Assumptions!$B$12 -> 24467.4 | O7: =M7+N7 -> 82967.4 | P7: =Assumptions!$B$32 -> 576000 | Q7: =Assumptions!$B$42 -> 850000 | R7: =IF(A7<=3,Assumptions!$B$40,Assumptions!$B$41) -> 100000 | S7: =Assumptions!$B$49 -> 257500 | T7: =P7+Q7+R7+S7 -> 1783500 | U7: =(CAPEX!$B$18+CAPEX!$B$20)/(Assumptions!$B$13*12)+IF(A7>=Assumptions!$B$56,Assumptions!$B$55/(Assumptions!$B$13*12),0) -> 301354.17 | V7: =L7-O7-T7-U7 -> -1261621.6 | W7: =V7 -> -1261621.6 | X7: =MAX(0,W7)*Assumptions!$B$14 -> 0 | Y7: =W7-X7 -> -1261621.6
A8: 5 | B8: =ROUNDUP(A8/12,0) -> 1 | C8: =G7 -> 41 | D8: =ROUND(IF(B8=1,Assumptions!$B$37,IF(B8=2,Assumptions!$B$38,Assumptions!$B$39))*MIN(1,A8/6),0) -> 13 | E8: =MAX(0,MIN(ROUND(D8*Assumptions!$B$35,0),Assumptions!$B$31-(C8-F8))) -> 7 | F8: =ROUND(C8*Assumptions!$B$36,0) -> 2 | G8: =MAX(0,MIN(Assumptions!$B$31,C8+E8-F8)) -> 46 | H8: =C8*Assumptions!$B$34 -> 697000 | I8: =E8*Assumptions!$B$8 -> 210000 | J8: =D8*Assumptions!$B$9 -> 28600 | K8: =C8*Assumptions!$B$43 -> 102500 | L8: =SUM(H8:K8) -> 1038100 | M8: =K8*Assumptions!$B$10 -> 66625 | N8: =L8*Assumptions!$B$11*Assumptions!$B$12 -> 28028.7 | O8: =M8+N8 -> 94653.7 | P8: =Assumptions!$B$32 -> 576000 | Q8: =Assumptions!$B$42 -> 850000 | R8: =IF(A8<=3,Assumptions!$B$40,Assumptions!$B$41) -> 100000 | S8: =Assumptions!$B$49 -> 257500 | T8: =P8+Q8+R8+S8 -> 1783500 | U8: =(CAPEX!$B$18+CAPEX!$B$20)/(Assumptions!$B$13*12)+IF(A8>=Assumptions!$B$56,Assumptions!$B$55/(Assumptions!$B$13*12),0) -> 301354.17 | V8: =L8-O8-T8-U8 -> -1141407.9 | W8: =V8 -> -1141407.9 | X8: =MAX(0,W8)*Assumptions!$B$14 -> 0 | Y8: =W8-X8 -> -1141407.9
A9: 6 | B9: =ROUNDUP(A9/12,0) -> 1 | C9: =G8 -> 46 | D9: =ROUND(IF(B9=1,Assumptions!$B$37,IF(B9=2,Assumptions!$B$38,Assumptions!$B$39))*MIN(1,A9/6),0) -> 16 | E9: =MAX(0,MIN(ROUND(D9*Assumptions!$B$35,0),Assumptions!$B$31-(C9-F9))) -> 9 | F9: =ROUND(C9*Assumptions!$B$36,0) -> 2 | G9: =MAX(0,MIN(Assumptions!$B$31,C9+E9-F9)) -> 53 | H9: =C9*Assumptions!$B$34 -> 782000 | I9: =E9*Assumptions!$B$8 -> 270000 | J9: =D9*Assumptions!$B$9 -> 35200 | K9: =C9*Assumptions!$B$43 -> 115000 | L9: =SUM(H9:K9) -> 1202200 | M9: =K9*Assumptions!$B$10 -> 74750 | N9: =L9*Assumptions!$B$11*Assumptions!$B$12 -> 32459.4 | O9: =M9+N9 -> 107209.4 | P9: =Assumptions!$B$32 -> 576000 | Q9: =Assumptions!$B$42 -> 850000 | R9: =IF(A9<=3,Assumptions!$B$40,Assumptions!$B$41) -> 100000 | S9: =Assumptions!$B$49 -> 257500 | T9: =P9+Q9+R9+S9 -> 1783500 | U9: =(CAPEX!$B$18+CAPEX!$B$20)/(Assumptions!$B$13*12)+IF(A9>=Assumptions!$B$56,Assumptions!$B$55/(Assumptions!$B$13*12),0) -> 306562.5 | V9: =L9-O9-T9-U9 -> -995071.9 | W9: =V9 -> -995071.9 | X9: =MAX(0,W9)*Assumptions!$B$14 -> 0 | Y9: =W9-X9 -> -995071.9
A10: 7 | B10: =ROUNDUP(A10/12,0) -> 1 | C10: =G9 -> 53 | D10: =ROUND(IF(B10=1,Assumptions!$B$37,IF(B10=2,Assumptions!$B$38,Assumptions!$B$39))*MIN(1,A10/6),0) -> 16 | E10: =MAX(0,MIN(ROUND(D10*Assumptions!$B$35,0),Assumptions!$B$31-(C10-F10))) -> 9 | F10: =ROUND(C10*Assumptions!$B$36,0) -> 2 | G10: =MAX(0,MIN(Assumptions!$B$31,C10+E10-F10)) -> 60 | H10: =C10*Assumptions!$B$34 -> 901000 | I10: =E10*Assumptions!$B$8 -> 270000 | J10: =D10*Assumptions!$B$9 -> 35200 | K10: =C10*Assumptions!$B$43 -> 132500 | L10: =SUM(H10:K10) -> 1338700 | M10: =K10*Assumptions!$B$10 -> 86125 | N10: =L10*Assumptions!$B$11*Assumptions!$B$12 -> 36144.9 | O10: =M10+N10 -> 122269.9 | P10: =Assumptions!$B$32 -> 576000 | Q10: =Assumptions!$B$42 -> 850000 | R10: =IF(A10<=3,Assumptions!$B$40,Assumptions!$B$41) -> 100000 | S10: =Assumptions!$B$49 -> 257500 | T10: =P10+Q10+R10+S10 -> 1783500 | U10: =(CAPEX!$B$18+CAPEX!$B$20)/(Assumptions!$B$13*12)+IF(A10>=Assumptions!$B$56,Assumptions!$B$55/(Assumptions!$B$13*12),0) -> 306562.5 | V10: =L10-O10-T10-U10 -> -873632.4 | W10: =V10 -> -873632.4 | X10: =MAX(0,W10)*Assumptions!$B$14 -> 0 | Y10: =W10-X10 -> -873632.4
A11: 8 | B11: =ROUNDUP(A11/12,0) -> 1 | C11: =G10 -> 60 | D11: =ROUND(IF(B11=1,Assumptions!$B$37,IF(B11=2,Assumptions!$B$38,Assumptions!$B$39))*MIN(1,A11/6),0) -> 16 | E11: =MAX(0,MIN(ROUND(D11*Assumptions!$B$35,0),Assumptions!$B$31-(C11-F11))) -> 9 | F11: =ROUND(C11*Assumptions!$B$36,0) -> 2 | G11: =MAX(0,MIN(Assumptions!$B$31,C11+E11-F11)) -> 67 | H11: =C11*Assumptions!$B$34 -> 1020000 | I11: =E11*Assumptions!$B$8 -> 270000 | J11: =D11*Assumptions!$B$9 -> 35200 | K11: =C11*Assumptions!$B$43 -> 150000 | L11: =SUM(H11:K11) -> 1475200 | M11: =K11*Assumptions!$B$10 -> 97500 | N11: =L11*Assumptions!$B$11*Assumptions!$B$12 -> 39830.4 | O11: =M11+N11 -> 137330.4 | P11: =Assumptions!$B$32 -> 576000 | Q11: =Assumptions!$B$42 -> 850000 | R11: =IF(A11<=3,Assumptions!$B$40,Assumptions!$B$41) -> 100000 | S11: =Assumptions!$B$49 -> 257500 | T11: =P11+Q11+R11+S11 -> 1783500 | U11: =(CAPEX!$B$18+CAPEX!$B$20)/(Assumptions!$B$13*12)+IF(A11>=Assumptions!$B$56,Assumptions!$B$55/(Assumptions!$B$13*12),0) -> 306562.5 | V11: =L11-O11-T11-U11 -> -752192.9 | W11: =V11 -> -752192.9 | X11: =MAX(0,W11)*Assumptions!$B$14 -> 0 | Y11: =W11-X11 -> -752192.9
A12: 9 | B12: =ROUNDUP(A12/12,0) -> 1 | C12: =G11 -> 67 | D12: =ROUND(IF(B12=1,Assumptions!$B$37,IF(B12=2,Assumptions!$B$38,Assumptions!$B$39))*MIN(1,A12/6),0) -> 16 | E12: =MAX(0,MIN(ROUND(D12*Assumptions!$B$35,0),Assumptions!$B$31-(C12-F12))) -> 9 | F12: =ROUND(C12*Assumptions!$B$36,0) -> 3 | G12: =MAX(0,MIN(Assumptions!$B$31,C12+E12-F12)) -> 73 | H12: =C12*Assumptions!$B$34 -> 1139000 | I12: =E12*Assumptions!$B$8 -> 270000 | J12: =D12*Assumptions!$B$9 -> 35200 | K12: =C12*Assumptions!$B$43 -> 167500 | L12: =SUM(H12:K12) -> 1611700 | M12: =K12*Assumptions!$B$10 -> 108875 | N12: =L12*Assumptions!$B$11*Assumptions!$B$12 -> 43515.9 | O12: =M12+N12 -> 152390.9 | P12: =Assumptions!$B$32 -> 576000 | Q12: =Assumptions!$B$42 -> 850000 | R12: =IF(A12<=3,Assumptions!$B$40,Assumptions!$B$41) -> 100000 | S12: =Assumptions!$B$49 -> 257500 | T12: =P12+Q12+R12+S12 -> 1783500 | U12: =(CAPEX!$B$18+CAPEX!$B$20)/(Assumptions!$B$13*12)+IF(A12>=Assumptions!$B$56,Assumptions!$B$55/(Assumptions!$B$13*12),0) -> 306562.5 | V12: =L12-O12-T12-U12 -> -630753.4 | W12: =V12 -> -630753.4 | X12: =MAX(0,W12)*Assumptions!$B$14 -> 0 | Y12: =W12-X12 -> -630753.4
A13: 10 | B13: =ROUNDUP(A13/12,0) -> 1 | C13: =G12 -> 73 | D13: =ROUND(IF(B13=1,Assumptions!$B$37,IF(B13=2,Assumptions!$B$38,Assumptions!$B$39))*MIN(1,A13/6),0) -> 16 | E13: =MAX(0,MIN(ROUND(D13*Assumptions!$B$35,0),Assumptions!$B$31-(C13-F13))) -> 9 | F13: =ROUND(C13*Assumptions!$B$36,0) -> 3 | G13: =MAX(0,MIN(Assumptions!$B$31,C13+E13-F13)) -> 79 | H13: =C13*Assumptions!$B$34 -> 1241000 | I13: =E13*Assumptions!$B$8 -> 270000 | J13: =D13*Assumptions!$B$9 -> 35200 | K13: =C13*Assumptions!$B$43 -> 182500 | L13: =SUM(H13:K13) -> 1728700 | M13: =K13*Assumptions!$B$10 -> 118625 | N13: =L13*Assumptions!$B$11*Assumptions!$B$12 -> 46674.9 | O13: =M13+N13 -> 165299.9 | P13: =Assumptions!$B$32 -> 576000 | Q13: =Assumptions!$B$42 -> 850000 | R13: =IF(A13<=3,Assumptions!$B$40,Assumptions!$B$41) -> 100000 | S13: =Assumptions!$B$49 -> 257500 | T13: =P13+Q13+R13+S13 -> 1783500 | U13: =(CAPEX!$B$18+CAPEX!$B$20)/(Assumptions!$B$13*12)+IF(A13>=Assumptions!$B$56,Assumptions!$B$55/(Assumptions!$B$13*12),0) -> 306562.5 | V13: =L13-O13-T13-U13 -> -526662.4 | W13: =V13 -> -526662.4 | X13: =MAX(0,W13)*Assumptions!$B$14 -> 0 | Y13: =W13-X13 -> -526662.4
A14: 11 | B14: =ROUNDUP(A14/12,0) -> 1 | C14: =G13 -> 79 | D14: =ROUND(IF(B14=1,Assumptions!$B$37,IF(B14=2,Assumptions!$B$38,Assumptions!$B$39))*MIN(1,A14/6),0) -> 16 | E14: =MAX(0,MIN(ROUND(D14*Assumptions!$B$35,0),Assumptions!$B$31-(C14-F14))) -> 9 | F14: =ROUND(C14*Assumptions!$B$36,0) -> 3 | G14: =MAX(0,MIN(Assumptions!$B$31,C14+E14-F14)) -> 85 | H14: =C14*Assumptions!$B$34 -> 1343000 | I14: =E14*Assumptions!$B$8 -> 270000 | J14: =D14*Assumptions!$B$9 -> 35200 | K14: =C14*Assumptions!$B$43 -> 197500 | L14: =SUM(H14:K14) -> 1845700 | M14: =K14*Assumptions!$B$10 -> 128375 | N14: =L14*Assumptions!$B$11*Assumptions!$B$12 -> 49833.9 | O14: =M14+N14 -> 178208.9 | P14: =Assumptions!$B$32 -> 576000 | Q14: =Assumptions!$B$42 -> 850000 | R14: =IF(A14<=3,Assumptions!$B$40,Assumptions!$B$41) -> 100000 | S14: =Assumptions!$B$49 -> 257500 | T14: =P14+Q14+R14+S14 -> 1783500 | U14: =(CAPEX!$B$18+CAPEX!$B$20)/(Assumptions!$B$13*12)+IF(A14>=Assumptions!$B$56,Assumptions!$B$55/(Assumptions!$B$13*12),0) -> 306562.5 | V14: =L14-O14-T14-U14 -> -422571.4 | W14: =V14 -> -422571.4 | X14: =MAX(0,W14)*Assumptions!$B$14 -> 0 | Y14: =W14-X14 -> -422571.4
A15: 12 | B15: =ROUNDUP(A15/12,0) -> 1 | C15: =G14 -> 85 | D15: =ROUND(IF(B15=1,Assumptions!$B$37,IF(B15=2,Assumptions!$B$38,Assumptions!$B$39))*MIN(1,A15/6),0) -> 16 | E15: =MAX(0,MIN(ROUND(D15*Assumptions!$B$35,0),Assumptions!$B$31-(C15-F15))) -> 9 | F15: =ROUND(C15*Assumptions!$B$36,0) -> 3 | G15: =MAX(0,MIN(Assumptions!$B$31,C15+E15-F15)) -> 91 | H15: =C15*Assumptions!$B$34 -> 1445000 | I15: =E15*Assumptions!$B$8 -> 270000 | J15: =D15*Assumptions!$B$9 -> 35200 | K15: =C15*Assumptions!$B$43 -> 212500 | L15: =SUM(H15:K15) -> 1962700 | M15: =K15*Assumptions!$B$10 -> 138125 | N15: =L15*Assumptions!$B$11*Assumptions!$B$12 -> 52992.9 | O15: =M15+N15 -> 191117.9 | P15: =Assumptions!$B$32 -> 576000 | Q15: =Assumptions!$B$42 -> 850000 | R15: =IF(A15<=3,Assumptions!$B$40,Assumptions!$B$41) -> 100000 | S15: =Assumptions!$B$49 -> 257500 | T15: =P15+Q15+R15+S15 -> 1783500 | U15: =(CAPEX!$B$18+CAPEX!$B$20)/(Assumptions!$B$13*12)+IF(A15>=Assumptions!$B$56,Assumptions!$B$55/(Assumptions!$B$13*12),0) -> 306562.5 | V15: =L15-O15-T15-U15 -> -318480.4 | W15: =V15 -> -318480.4 | X15: =MAX(0,W15)*Assumptions!$B$14 -> 0 | Y15: =W15-X15 -> -318480.4
A16: 13 | B16: =ROUNDUP(A16/12,0) -> 2 | C16: =G15 -> 91 | D16: =ROUND(IF(B16=1,Assumptions!$B$37,IF(B16=2,Assumptions!$B$38,Assumptions!$B$39))*MIN(1,A16/6),0) -> 22 | E16: =MAX(0,MIN(ROUND(D16*Assumptions!$B$35,0),Assumptions!$B$31-(C16-F16))) -> 12 | F16: =ROUND(C16*Assumptions!$B$36,0) -> 4 | G16: =MAX(0,MIN(Assumptions!$B$31,C16+E16-F16)) -> 99 | H16: =C16*Assumptions!$B$34 -> 1547000 | I16: =E16*Assumptions!$B$8 -> 360000 | J16: =D16*Assumptions!$B$9 -> 48400 | K16: =C16*Assumptions!$B$43 -> 227500 | L16: =SUM(H16:K16) -> 2182900 | M16: =K16*Assumptions!$B$10 -> 147875 | N16: =L16*Assumptions!$B$11*Assumptions!$B$12 -> 58938.3 | O16: =M16+N16 -> 206813.3 | P16: =Assumptions!$B$32 -> 576000 | Q16: =Assumptions!$B$42 -> 850000 | R16: =IF(A16<=3,Assumptions!$B$40,Assumptions!$B$41) -> 100000 | S16: =Assumptions!$B$49 -> 257500 | T16: =P16+Q16+R16+S16 -> 1783500 | U16: =(CAPEX!$B$18+CAPEX!$B$20)/(Assumptions!$B$13*12)+IF(A16>=Assumptions!$B$56,Assumptions!$B$55/(Assumptions!$B$13*12),0) -> 306562.5 | V16: =L16-O16-T16-U16 -> -113975.8 | W16: =V16 -> -113975.8 | X16: =MAX(0,W16)*Assumptions!$B$14 -> 0 | Y16: =W16-X16 -> -113975.8
... A39: 36 | B39: =ROUNDUP(A39/12,0) -> 3 | C39: =G38 -> 180 | D39: =ROUND(IF(B39=1,Assumptions!$B$37,IF(B39=2,Assumptions!$B$38,Assumptions!$B$39))*MIN(1,A39/6),0) -> 26 | E39: =MAX(0,MIN(ROUND(D39*Assumptions!$B$35,0),Assumptions!$B$31-(C39-F39))) -> 7 | F39: =ROUND(C39*Assumptions!$B$36,0) -> 7 | G39: =MAX(0,MIN(Assumptions!$B$31,C39+E39-F39)) -> 180 | H39: =C39*Assumptions!$B$34 -> 3060000 | I39: =E39*Assumptions!$B$8 -> 210000 | J39: =D39*Assumptions!$B$9 -> 57200 | K39: =C39*Assumptions!$B$43 -> 450000 | L39: =SUM(H39:K39) -> 3777200 | M39: =K39*Assumptions!$B$10 -> 292500 | N39: =L39*Assumptions!$B$11*Assumptions!$B$12 -> 101984.4 | O39: =M39+N39 -> 394484.4 | P39: =Assumptions!$B$32 -> 576000 | Q39: =Assumptions!$B$42 -> 850000 | R39: =IF(A39<=3,Assumptions!$B$40,Assumptions!$B$41) -> 100000 | S39: =Assumptions!$B$49 -> 257500 | T39: =P39+Q39+R39+S39 -> 1783500 | U39: =(CAPEX!$B$18+CAPEX!$B$20)/(Assumptions!$B$13*12)+IF(A39>=Assumptions!$B$56,Assumptions!$B$55/(Assumptions!$B$13*12),0) -> 306562.5 | V39: =L39-O39-T39-U39 -> 1292653.1 | W39: =V39 -> 1292653.1 | X39: =MAX(0,W39)*Assumptions!$B$14 -> 387795.93 | Y39: =W39-X39 -> 904857.17

Sheet Cash_Flow
A1: 月次キャッシュフロー
A2: 期末現金マイナス=資金ショート(赤)。営業CF=税引後+減価償却。前受け=運転資本。
A3: 月 | B3: 営業CF | C3: 投資CF | D3: 財務CF | E3: 前受けCF(運転資本) | F3: 純増減 | G3: 期末現金 | H3: 累計営業CF | I3: 回収判定(内部)
A4: 0 | B4: 0 | C4: =-CAPEX!$B$21 -> -32386000 | D4: =Assumptions!$B$28+Assumptions!$B$29 -> 20000000 | E4: 0 | F4: =B4+C4+D4+E4 -> -12386000 | G4: =F4 -> -12386000 | H4: 0 | I4: 9999
A5: 1 | B5: =Monthly_PL!$Y4+Monthly_PL!$U4 -> -1278243.2 | C5: =IF(A5=Assumptions!$B$56,-Assumptions!$B$55,0) -> 0 | D5: 0 | E5: =Assumptions!$B$52*Assumptions!$B$53*Assumptions!$B$34*(Monthly_PL!$G$4-0) -> 790500 | F5: =B5+C5+D5+E5 -> -487743.2 | G5: =G4+F5 -> -12873743 | H5: =SUM($B$5:B5) -> -1278243.2 | I5: =IF(H5>=CAPEX!$B$21,A5,9999) -> 9999
A6: 2 | B6: =Monthly_PL!$Y5+Monthly_PL!$U5 -> -1227423.5 | C6: =IF(A6=Assumptions!$B$56,-Assumptions!$B$55,0) -> 0 | D6: 0 | E6: =Assumptions!$B$52*Assumptions!$B$53*Assumptions!$B$34*(Monthly_PL!$G$5-Monthly_PL!$G$4) -> 51000 | F6: =B6+C6+D6+E6 -> -1176423.5 | G6: =G5+F6 -> -14050167 | H6: =SUM($B$5:B6) -> -2505666.7 | I6: =IF(H6>=CAPEX!$B$21,A6,9999) -> 9999
A7: 3 | B7: =Monthly_PL!$Y6+Monthly_PL!$U6 -> -1157114.7 | C7: =IF(A7=Assumptions!$B$56,-Assumptions!$B$55,0) -> 0 | D7: 0 | E7: =Assumptions!$B$52*Assumptions!$B$53*Assumptions!$B$34*(Monthly_PL!$G$6-Monthly_PL!$G$5) -> 76500 | F7: =B7+C7+D7+E7 -> -1080614.7 | G7: =G6+F7 -> -15130781 | H7: =SUM($B$5:B7) -> -3662781.4 | I7: =IF(H7>=CAPEX!$B$21,A7,9999) -> 9999
A8: 4 | B8: =Monthly_PL!$Y7+Monthly_PL!$U7 -> -960267.4 | C8: =IF(A8=Assumptions!$B$56,-Assumptions!$B$55,0) -> 0 | D8: 0 | E8: =Assumptions!$B$52*Assumptions!$B$53*Assumptions!$B$34*(Monthly_PL!$G$7-Monthly_PL!$G$6) -> 127500 | F8: =B8+C8+D8+E8 -> -832767.4 | G8: =G7+F8 -> -15963549 | H8: =SUM($B$5:B8) -> -4623048.8 | I8: =IF(H8>=CAPEX!$B$21,A8,9999) -> 9999
A9: 5 | B9: =Monthly_PL!$Y8+Monthly_PL!$U8 -> -840053.7 | C9: =IF(A9=Assumptions!$B$56,-Assumptions!$B$55,0) -> 0 | D9: 0 | E9: =Assumptions!$B$52*Assumptions!$B$53*Assumptions!$B$34*(Monthly_PL!$G$8-Monthly_PL!$G$7) -> 127500 | F9: =B9+C9+D9+E9 -> -712553.7 | G9: =G8+F9 -> -16676102 | H9: =SUM($B$5:B9) -> -5463102.5 | I9: =IF(H9>=CAPEX!$B$21,A9,9999) -> 9999
A10: 6 | B10: =Monthly_PL!$Y9+Monthly_PL!$U9 -> -688509.4 | C10: =IF(A10=Assumptions!$B$56,-Assumptions!$B$55,0) -> -500000 | D10: 0 | E10: =Assumptions!$B$52*Assumptions!$B$53*Assumptions!$B$34*(Monthly_PL!$G$9-Monthly_PL!$G$8) -> 178500 | F10: =B10+C10+D10+E10 -> -1010009.4 | G10: =G9+F10 -> -17686112 | H10: =SUM($B$5:B10) -> -6151611.9 | I10: =IF(H10>=CAPEX!$B$21,A10,9999) -> 9999
A11: 7 | B11: =Monthly_PL!$Y10+Monthly_PL!$U10 -> -567069.9 | C11: =IF(A11=Assumptions!$B$56,-Assumptions!$B$55,0) -> 0 | D11: 0 | E11: =Assumptions!$B$52*Assumptions!$B$53*Assumptions!$B$34*(Monthly_PL!$G$10-Monthly_PL!$G$9) -> 178500 | F11: =B11+C11+D11+E11 -> -388569.9 | G11: =G10+F11 -> -18074682 | H11: =SUM($B$5:B11) -> -6718681.8 | I11: =IF(H11>=CAPEX!$B$21,A11,9999) -> 9999
A12: 8 | B12: =Monthly_PL!$Y11+Monthly_PL!$U11 -> -445630.4 | C12: =IF(A12=Assumptions!$B$56,-Assumptions!$B$55,0) -> 0 | D12: 0 | E12: =Assumptions!$B$52*Assumptions!$B$53*Assumptions!$B$34*(Monthly_PL!$G$11-Monthly_PL!$G$10) -> 178500 | F12: =B12+C12+D12+E12 -> -267130.4 | G12: =G11+F12 -> -18341812 | H12: =SUM($B$5:B12) -> -7164312.2 | I12: =IF(H12>=CAPEX!$B$21,A12,9999) -> 9999
A13: 9 | B13: =Monthly_PL!$Y12+Monthly_PL!$U12 -> -324190.9 | C13: =IF(A13=Assumptions!$B$56,-Assumptions!$B$55,0) -> 0 | D13: 0 | E13: =Assumptions!$B$52*Assumptions!$B$53*Assumptions!$B$34*(Monthly_PL!$G$12-Monthly_PL!$G$11) -> 153000 | F13: =B13+C13+D13+E13 -> -171190.9 | G13: =G12+F13 -> -18513003 | H13: =SUM($B$5:B13) -> -7488503.1 | I13: =IF(H13>=CAPEX!$B$21,A13,9999) -> 9999
A14: 10 | B14: =Monthly_PL!$Y13+Monthly_PL!$U13 -> -220099.9 | C14: =IF(A14=Assumptions!$B$56,-Assumptions!$B$55,0) -> 0 | D14: 0 | E14: =Assumptions!$B$52*Assumptions!$B$53*Assumptions!$B$34*(Monthly_PL!$G$13-Monthly_PL!$G$12) -> 153000 | F14: =B14+C14+D14+E14 -> -67099.9 | G14: =G13+F14 -> -18580103 | H14: =SUM($B$5:B14) -> -7708603 | I14: =IF(H14>=CAPEX!$B$21,A14,9999) -> 9999
A15: 11 | B15: =Monthly_PL!$Y14+Monthly_PL!$U14 -> -116008.9 | C15: =IF(A15=Assumptions!$B$56,-Assumptions!$B$55,0) -> 0 | D15: 0 | E15: =Assumptions!$B$52*Assumptions!$B$53*Assumptions!$B$34*(Monthly_PL!$G$14-Monthly_PL!$G$13) -> 153000 | F15: =B15+C15+D15+E15 -> 36991.1 | G15: =G14+F15 -> -18543112 | H15: =SUM($B$5:B15) -> -7824611.9 | I15: =IF(H15>=CAPEX!$B$21,A15,9999) -> 9999
A16: 12 | B16: =Monthly_PL!$Y15+Monthly_PL!$U15 -> -11917.9 | C16: =IF(A16=Assumptions!$B$56,-Assumptions!$B$55,0) -> 0 | D16: 0 | E16: =Assumptions!$B$52*Assumptions!$B$53*Assumptions!$B$34*(Monthly_PL!$G$15-Monthly_PL!$G$14) -> 153000 | F16: =B16+C16+D16+E16 -> 141082.1 | G16: =G15+F16 -> -18402030 | H16: =SUM($B$5:B16) -> -7836529.8 | I16: =IF(H16>=CAPEX!$B$21,A16,9999) -> 9999
A17: 13 | B17: =Monthly_PL!$Y16+Monthly_PL!$U16 -> 192586.7 | C17: =IF(A17=Assumptions!$B$56,-Assumptions!$B$55,0) -> 0 | D17: 0 | E17: =Assumptions!$B$52*Assumptions!$B$53*Assumptions!$B$34*(Monthly_PL!$G$16-Monthly_PL!$G$15) -> 204000 | F17: =B17+C17+D17+E17 -> 396586.7 | G17: =G16+F17 -> -18005443 | H17: =SUM($B$5:B17) -> -7643943.1 | I17: =IF(H17>=CAPEX!$B$21,A17,9999) -> 9999
A18: 14 | B18: =Monthly_PL!$Y17+Monthly_PL!$U17 -> 323931.04 | C18: =IF(A18=Assumptions!$B$56,-Assumptions!$B$55,0) -> 0 | D18: 0 | E18: =Assumptions!$B$52*Assumptions!$B$53*Assumptions!$B$34*(Monthly_PL!$G$17-Monthly_PL!$G$16) -> 204000 | F18: =B18+C18+D18+E18 -> 527931.04 | G18: =G17+F18 -> -17477512 | H18: =SUM($B$5:B18) -> -7320012.1 | I18: =IF(H18>=CAPEX!$B$21,A18,9999) -> 9999
A19: 15 | B19: =Monthly_PL!$Y18+Monthly_PL!$U18 -> 421082.64 | C19: =IF(A19=Assumptions!$B$56,-Assumptions!$B$55,0) -> 0 | D19: 0 | E19: =Assumptions!$B$52*Assumptions!$B$53*Assumptions!$B$34*(Monthly_PL!$G$18-Monthly_PL!$G$17) -> 204000 | F19: =B19+C19+D19+E19 -> 625082.64 | G19: =G18+F19 -> -16852429 | H19: =SUM($B$5:B19) -> -6898929.4 | I19: =IF(H19>=CAPEX!$B$21,A19,9999) -> 9999
A20: 16 | B20: =Monthly_PL!$Y19+Monthly_PL!$U19 -> 518234.24 | C20: =IF(A20=Assumptions!$B$56,-Assumptions!$B$55,0) -> 0 | D20: 0 | E20: =Assumptions!$B$52*Assumptions!$B$53*Assumptions!$B$34*(Monthly_PL!$G$19-Monthly_PL!$G$18) -> 178500 | F20: =B20+C20+D20+E20 -> 696734.24 | G20: =G19+F20 -> -16155695 | H20: =SUM($B$5:B20) -> -6380695.2 | I20: =IF(H20>=CAPEX!$B$21,A20,9999) -> 9999
A21: 17 | B21: =Monthly_PL!$Y20+Monthly_PL!$U20 -> 603241.89 | C21: =IF(A21=Assumptions!$B$56,-Assumptions!$B$55,0) -> 0 | D21: 0 | E21: =Assumptions!$B$52*Assumptions!$B$53*Assumptions!$B$34*(Monthly_PL!$G$20-Monthly_PL!$G$19) -> 178500 | F21: =B21+C21+D21+E21 -> 781741.89 | G21: =G20+F21 -> -15373953 | H21: =SUM($B$5:B21) -> -5777453.3 | I21: =IF(H21>=CAPEX!$B$21,A21,9999) -> 9999
A22: 18 | B22: =Monthly_PL!$Y21+Monthly_PL!$U21 -> 688249.54 | C22: =IF(A22=Assumptions!$B$56,-Assumptions!$B$55,0) -> 0 | D22: 0 | E22: =Assumptions!$B$52*Assumptions!$B$53*Assumptions!$B$34*(Monthly_PL!$G$21-Monthly_PL!$G$20) -> 178500 | F22: =B22+C22+D22+E22 -> 866749.54 | G22: =G21+F22 -> -14507204 | H22: =SUM($B$5:B22) -> -5089203.8 | I22: =IF(H22>=CAPEX!$B$21,A22,9999) -> 9999
A23: 19 | B23: =Monthly_PL!$Y22+Monthly_PL!$U22 -> 773257.19 | C23: =IF(A23=Assumptions!$B$56,-Assumptions!$B$55,0) -> 0 | D23: 0 | E23: =Assumptions!$B$52*Assumptions!$B$53*Assumptions!$B$34*(Monthly_PL!$G$22-Monthly_PL!$G$21) -> 178500 | F23: =B23+C23+D23+E23 -> 951757.19 | G23: =G22+F23 -> -13555447 | H23: =SUM($B$5:B23) -> -4315946.6 | I23: =IF(H23>=CAPEX!$B$21,A23,9999) -> 9999
A24: 20 | B24: =Monthly_PL!$Y23+Monthly_PL!$U23 -> 858264.84 | C24: =IF(A24=Assumptions!$B$56,-Assumptions!$B$55,0) -> 0 | D24: 0 | E24: =Assumptions!$B$52*Assumptions!$B$53*Assumptions!$B$34*(Monthly_PL!$G$23-Monthly_PL!$G$22) -> 153000 | F24: =B24+C24+D24+E24 -> 1011264.8 | G24: =G23+F24 -> -12544182 | H24: =SUM($B$5:B24) -> -3457681.7 | I24: =IF(H24>=CAPEX!$B$21,A24,9999) -> 9999
A25: 21 | B25: =Monthly_PL!$Y24+Monthly_PL!$U24 -> 931128.54 | C25: =IF(A25=Assumptions!$B$56,-Assumptions!$B$55,0) -> 0 | D25: 0 | E25: =Assumptions!$B$52*Assumptions!$B$53*Assumptions!$B$34*(Monthly_PL!$G$24-Monthly_PL!$G$23) -> 153000 | F25: =B25+C25+D25+E25 -> 1084128.5 | G25: =G24+F25 -> -11460053 | H25: =SUM($B$5:B25) -> -2526553.2 | I25: =IF(H25>=CAPEX!$B$21,A25,9999) -> 9999
A26: 22 | B26: =Monthly_PL!$Y25+Monthly_PL!$U25 -> 1003992.2 | C26: =IF(A26=Assumptions!$B$56,-Assumptions!$B$55,0) -> 0 | D26: 0 | E26: =Assumptions!$B$52*Assumptions!$B$53*Assumptions!$B$34*(Monthly_PL!$G$25-Monthly_PL!$G$24) -> 153000 | F26: =B26+C26+D26+E26 -> 1156992.2 | G26: =G25+F26 -> -10303061 | H26: =SUM($B$5:B26) -> -1522560.9 | I26: =IF(H26>=CAPEX!$B$21,A26,9999) -> 9999
A27: 23 | B27: =Monthly_PL!$Y26+Monthly_PL!$U26 -> 1076855.9 | C27: =IF(A27=Assumptions!$B$56,-Assumptions!$B$55,0) -> 0 | D27: 0 | E27: =Assumptions!$B$52*Assumptions!$B$53*Assumptions!$B$34*(Monthly_PL!$G$26-Monthly_PL!$G$25) -> 153000 | F27: =B27+C27+D27+E27 -> 1229855.9 | G27: =G26+F27 -> -9073205 | H27: =SUM($B$5:B27) -> -445705 | I27: =IF(H27>=CAPEX!$B$21,A27,9999) -> 9999
A28: 24 | B28: =Monthly_PL!$Y27+Monthly_PL!$U27 -> 1149719.6 | C28: =IF(A28=Assumptions!$B$56,-Assumptions!$B$55,0) -> 0 | D28: 0 | E28: =Assumptions!$B$52*Assumptions!$B$53*Assumptions!$B$34*(Monthly_PL!$G$27-Monthly_PL!$G$26) -> 127500 | F28: =B28+C28+D28+E28 -> 1277219.6 | G28: =G27+F28 -> -7795985.4 | H28: =SUM($B$5:B28) -> 704014.64 | I28: =IF(H28>=CAPEX!$B$21,A28,9999) -> 9999
A29: 25 | B29: =Monthly_PL!$Y28+Monthly_PL!$U28 -> 1257299.1 | C29: =IF(A29=Assumptions!$B$56,-Assumptions!$B$55,0) -> 0 | D29: 0 | E29: =Assumptions!$B$52*Assumptions!$B$53*Assumptions!$B$34*(Monthly_PL!$G$28-Monthly_PL!$G$27) -> 178500 | F29: =B29+C29+D29+E29 -> 1435799.1 | G29: =G28+F29 -> -6360186.3 | H29: =SUM($B$5:B29) -> 1961313.7 | I29: =IF(H29>=CAPEX!$B$21,A29,9999) -> 9999
A30: 26 | B30: =Monthly_PL!$Y29+Monthly_PL!$U29 -> 1219708.7 | C30: =IF(A30=Assumptions!$B$56,-Assumptions!$B$55,0) -> 0 | D30: 0 | E30: =Assumptions!$B$52*Assumptions!$B$53*Assumptions!$B$34*(Monthly_PL!$G$29-Monthly_PL!$G$28) -> 25500 | F30: =B30+C30+D30+E30 -> 1245208.7 | G30: =G29+F30 -> -5114977.6 | H30: =SUM($B$5:B30) -> 3181022.4 | I30: =IF(H30>=CAPEX!$B$21,A30,9999) -> 9999
A31: 27 | B31: =Monthly_PL!$Y30+Monthly_PL!$U30 -> 1211419.7 | C31: =IF(A31=Assumptions!$B$56,-Assumptions!$B$55,0) -> 0 | D31: 0 | E31: =Assumptions!$B$52*Assumptions!$B$53*Assumptions!$B$34*(Monthly_PL!$G$30-Monthly_PL!$G$29) -> 0 | F31: =B31+C31+D31+E31 -> 1211419.7 | G31: =G30+F31 -> -3903557.9 | H31: =SUM($B$5:B31) -> 4392442.1 | I31: =IF(H31>=CAPEX!$B$21,A31,9999) -> 9999
A32: 28 | B32: =Monthly_PL!$Y31+Monthly_PL!$U31 -> 1211419.7 | C32: =IF(A32=Assumptions!$B$56,-Assumptions!$B$55,0) -> 0 | D32: 0 | E32: =Assumptions!$B$52*Assumptions!$B$53*Assumptions!$B$34*(Monthly_PL!$G$31-Monthly_PL!$G$30) -> 0 | F32: =B32+C32+D32+E32 -> 1211419.7 | G32: =G31+F32 -> -2692138.2 | H32: =SUM($B$5:B32) -> 5603861.8 | I32: =IF(H32>=CAPEX!$B$21,A32,9999) -> 9999
A33: 29 | B33: =Monthly_PL!$Y32+Monthly_PL!$U32 -> 1211419.7 | C33: =IF(A33=Assumptions!$B$56,-Assumptions!$B$55,0) -> 0 | D33: 0 | E33: =Assumptions!$B$52*Assumptions!$B$53*Assumptions!$B$34*(Monthly_PL!$G$32-Monthly_PL!$G$31) -> 0 | F33: =B33+C33+D33+E33 -> 1211419.7 | G33: =G32+F33 -> -1480718.6 | H33: =SUM($B$5:B33) -> 6815281.4 | I33: =IF(H33>=CAPEX!$B$21,A33,9999) -> 9999
A34: 30 | B34: =Monthly_PL!$Y33+Monthly_PL!$U33 -> 1211419.7 | C34: =IF(A34=Assumptions!$B$56,-Assumptions!$B$55,0) -> 0 | D34: 0 | E34: =Assumptions!$B$52*Assumptions!$B$53*Assumptions!$B$34*(Monthly_PL!$G$33-Monthly_PL!$G$32) -> 0 | F34: =B34+C34+D34+E34 -> 1211419.7 | G34: =G33+F34 -> -269298.89 | H34: =SUM($B$5:B34) -> 8026701.1 | I34: =IF(H34>=CAPEX!$B$21,A34,9999) -> 9999
A35: 31 | B35: =Monthly_PL!$Y34+Monthly_PL!$U34 -> 1211419.7 | C35: =IF(A35=Assumptions!$B$56,-Assumptions!$B$55,0) -> 0 | D35: 0 | E35: =Assumptions!$B$52*Assumptions!$B$53*Assumptions!$B$34*(Monthly_PL!$G$34-Monthly_PL!$G$33) -> 0 | F35: =B35+C35+D35+E35 -> 1211419.7 | G35: =G34+F35 -> 942120.78 | H35: =SUM($B$5:B35) -> 9238120.8 | I35: =IF(H35>=CAPEX!$B$21,A35,9999) -> 9999
A36: 32 | B36: =Monthly_PL!$Y35+Monthly_PL!$U35 -> 1211419.7 | C36: =IF(A36=Assumptions!$B$56,-Assumptions!$B$55,0) -> 0 | D36: 0 | E36: =Assumptions!$B$52*Assumptions!$B$53*Assumptions!$B$34*(Monthly_PL!$G$35-Monthly_PL!$G$34) -> 0 | F36: =B36+C36+D36+E36 -> 1211419.7 | G36: =G35+F36 -> 2153540.5 | H36: =SUM($B$5:B36) -> 10449540 | I36: =IF(H36>=CAPEX!$B$21,A36,9999) -> 9999
A37: 33 | B37: =Monthly_PL!$Y36+Monthly_PL!$U36 -> 1211419.7 | C37: =IF(A37=Assumptions!$B$56,-Assumptions!$B$55,0) -> 0 | D37: 0 | E37: =Assumptions!$B$52*Assumptions!$B$53*Assumptions!$B$34*(Monthly_PL!$G$36-Monthly_PL!$G$35) -> 0 | F37: =B37+C37+D37+E37 -> 1211419.7 | G37: =G36+F37 -> 3364960.1 | H37: =SUM($B$5:B37) -> 11660960 | I37: =IF(H37>=CAPEX!$B$21,A37,9999) -> 9999
A38: 34 | B38: =Monthly_PL!$Y37+Monthly_PL!$U37 -> 1211419.7 | C38: =IF(A38=Assumptions!$B$56,-Assumptions!$B$55,0) -> 0 | D38: 0 | E38: =Assumptions!$B$52*Assumptions!$B$53*Assumptions!$B$34*(Monthly_PL!$G$37-Monthly_PL!$G$36) -> 0 | F38: =B38+C38+D38+E38 -> 1211419.7 | G38: =G37+F38 -> 4576379.8 | H38: =SUM($B$5:B38) -> 12872380 | I38: =IF(H38>=CAPEX!$B$21,A38,9999) -> 9999
A39: 35 | B39: =Monthly_PL!$Y38+Monthly_PL!$U38 -> 1211419.7 | C39: =IF(A39=Assumptions!$B$56,-Assumptions!$B$55,0) -> 0 | D39: 0 | E39: =Assumptions!$B$52*Assumptions!$B$53*Assumptions!$B$34*(Monthly_PL!$G$38-Monthly_PL!$G$37) -> 0 | F39: =B39+C39+D39+E39 -> 1211419.7 | G39: =G38+F39 -> 5787799.5 | H39: =SUM($B$5:B39) -> 14083799 | I39: =IF(H39>=CAPEX!$B$21,A39,9999) -> 9999
A40: 36 | B40: =Monthly_PL!$Y39+Monthly_PL!$U39 -> 1211419.7 | C40: =IF(A40=Assumptions!$B$56,-Assumptions!$B$55,0) -> 0 | D40: 0 | E40: =Assumptions!$B$52*Assumptions!$B$53*Assumptions!$B$34*(Monthly_PL!$G$39-Monthly_PL!$G$38) -> 0 | F40: =B40+C40+D40+E40 -> 1211419.7 | G40: =G39+F40 -> 6999219.1 | H40: =SUM($B$5:B40) -> 15295219 | I40: =IF(H40>=CAPEX!$B$21,A40,9999) -> 9999

Sheet BreakEven
A1: 損益分岐点分析
A2: 月固定費(定常/4ヶ月〜) | B2: =Assumptions!$B$32+Assumptions!$B$42+Assumptions!$B$41+Assumptions!$B$49 -> 1783500
A3: 平均月会費(税抜) | B3: =Assumptions!$B$34 -> 17000
A4: 物販ARPU | B4: =Assumptions!$B$43 -> 2500
A5: 物販原価率 | B5: =Assumptions!$B$10 -> 0.65
A6: 決済実効率 | B6: =Assumptions!$B$11*Assumptions!$B$12 -> 0.027
A7: 会員あたり月次貢献 | B7: =B3*(1-B6)+B4*(1-B5)-B4*B6 -> 17348.5
A8: 損益分岐点 会員数 | B8: =ROUNDUP(B2/B7,0) -> 103
A9: 会員上限(打席×係数) | B9: =Assumptions!$B$31 -> 180
A10: 必要月商(概算) | B10: =B8*(B3+B4) -> 2008500
A11: 現状会員(36ヶ月) | B11: =Monthly_PL!$G$39 -> 180
A12: BEP維持に必要な月間入会 | B12: =ROUNDUP(B8*Assumptions!$B$36,0) -> 5
A13: 必要月間体験数 | B13: =ROUNDUP(B12/Assumptions!$B$35,0) -> 10

Sheet Sensitivity
A1: 感応度分析（年間営業利益への影響・一次近似）
A2: 精緻な再計算はAssumptions変更→Summaryで確認。下表は目安
A4: 基準:年間営業利益(Y3) | B4: =SUM(Monthly_PL!$V$28:$V$39) -> 15589221
A6: 変動要因 | B6: 変化幅 | C6: 年間営業利益への影響(近似)
A7: 打席数 | B7: +1打席(会員上限+係数) | C7: =Assumptions!$B$7*BreakEven!$B$7*12 -> 9368190
A8: 会員数 | B8: +10% | C8: =0.1*Monthly_PL!$G$39*BreakEven!$B$7*12 -> 3747276
A9: 平均月会費 | B9: +1,000円 | C9: =Monthly_PL!$G$39*1000*(1-Assumptions!$B$11*Assumptions!$B$12)*12 -> 2101680
A10: 退会率 | B10: +2pt | C10: =-Monthly_PL!$G$39*0.02*BreakEven!$B$7*12 -> -749455.2
A11: 人件費 | B11: +10% | C11: =-Assumptions!$B$42*0.1*12 -> -1020000
A12: 家賃 | B12: +10% | C12: =-Assumptions!$B$32*0.1*12 -> -691200
A13: 内装坪単価 | B13: +5万/坪 | C13: =-Assumptions!$B$6*50000/(Assumptions!$B$13*12)*12 -> -300000

Sheet Risks
A1: リスク一覧
A3: 分類 | B3: リスク | C3: 影響度 | D3: 発生可能性 | E3: 対策
A4: 出店 | B4: 駐車場(打席×2台)確保が困難 | C4: 高 | D4: 高 | E4: 探索条件緩和・近隣コインP併用・打席数調整
A5: 資金 | B5: 非居抜き内装で初期投資が膨らむ | C5: 高 | D5: 高 | E5: 内装坪単価精査・打席数縮小・段階投資・融資増額
A6: 資金 | B6: 融資が下りない/条件悪い | C6: 高 | D6: 中 | E6: 複数行並行・公庫＋民間・自己資金比率UP
A7: 集客 | B7: 初年度立ち上がり遅延 | C7: 高 | D7: 中 | E7: 相互利用告知・紹介・体験導線・広告前倒し
A8: 運営 | B8: 退会率上昇 | C8: 高 | D8: 中 | E8: 予約改善・レッスン価値・相互利用の利便性
A9: 設備 | B9: 機材納期(3-5打席分) | C9: 中 | D9: 中 | E9: 早期発注・段階開業・リース
A10: 法務 | B10: ブランド/相互利用条件の相違 | C10: 高 | D10: 中 | E10: ファインと書面合意
A11: 近隣 | B11: 騒音クレーム | C11: 中 | D11: 低 | E11: 事前騒音測定・防音余裕設計
A12: ブランド | B12: 品質ばらつきでGOLF WING毀損 | C12: 高 | D12: 中 | E12: SOP・KPI監視・是正フロー

Sheet Investor_QA
A1: 想定問答
A3: 想定質問 | B3: 回答案
A4: なぜ非居抜きで高い投資を? | B4: 宝塚10km圏の相互利用で会員利便と定着を高める立地優先。内装は坪単価を精査し打席数で調整可能。
A5: 必要資金と調達は? | B5: 打席数・坪数で総初期投資が自動算出。出資＋融資＋自己資金で構成し、融資内諾を契約の前提とする。
A6: 売上前提は妥当か? | B6: 8月値上げ後料金×会員構成。入会率・退会率は宝塚実績を保守補正。悲観/最悪で耐性確認。
A7: 相互利用の効果は? | B7: 宝塚会員の一部が移行・併用し初速を確保。ただし会費/KPI帰属はファインと事前合意。
A8: 打席数は何面が最適? | B8: 打席数を変えると必要資金・会員上限・損益分岐点が自動更新。3/4/5で比較し投資対効果で決定。
A9: 資金ショートは? | B9: Cash_Flowで月末現金を可視化、赤表示。前受けで運転資本を改善。
